[{"date":"2020.11.03","time":"09:05:11","latitude":"37.8435","longitude":"26.7087","depth":"5.1","md":"-.-","ml":"2.5","mw":"-.-","location":"EGE DENIZI"},{"date":"2020.11.03","time":"09:03:27","latitude":"37.7430","longitude":"27.0718","depth":"7.6","md":"-.-","ml":"1.8","mw":"-.-","location":"KUSADASI KORFEZI (EGE DENIZI)"},{"date":"2020.11.03","time":"08:52:24","latitude":"37.8982","longitude":"26.8773","depth":"6.3","md":"-.-","ml":"2.1","mw":"-.-","location":"KUSADASI KORFEZI (EGE DENIZI)"},{"date":"2020.11.03","time":"08:32:52","latitude":"37.8172","longitude":"26.9950","depth":"7.9","md":"-.-","ml":"3.4","mw":"3.3","location":"KUSADASI KORFEZI (EGE DENIZI)"},{"date":"2020.11.03","time":"08:31:32","latitude":"38.0057","longitude":"27.6242","depth":"14.9","md":"-.-","ml":"1.8","mw":"-.-","location":"HABIBLER-GERMENCIK (AYDIN)"},{"date":"2020.11.03","time":"08:28:06","latitude":"40.2522","longitude":"42.6905","depth":"5.8","md":"-.-","ml":"2.6","mw":"-.-","location":"SEHITEMIN-SARIKAMIS (KARS)"},{"date":"2020.11.03","time":"08:19:37","latitude":"37.9043","longitude":"26.9300","depth":"10.2","md":"-.-","ml":"2.2","mw":"-.-","location":"KUSADASI KORFEZI (EGE DENIZI)"},{"date":"2020.11.03","time":"08:12:47","latitude":"37.7250","longitude":"27.0098","depth":"3.7","md":"-.-","ml":"2.3","mw":"-.-","location":"SISAM ADASI (EGE DENIZI)"},{"date":"2020.11.03","time":"08:09:12","latitude":"37.7237","longitude":"26.9792","depth":"7.4","md":"-.-","ml":"2.1","mw":"-.-","location":"SISAM ADASI (EGE DENIZI)"},{"date":"2020.11.03","time":"08:07:19","latitude":"37.8757","longitude":"26.9075","depth":"4.2","md":"-.-","ml":"2.4","mw":"-.-","location":"KUSADASI KORFEZI (EGE DENIZI)"},{"date":"2020.11.03","time":"07:59:12","latitude":"37.8675","longitude":"26.9338","depth":"6.9","md":"-.-","ml":"2.0","mw":"-.-","location":"KUSADASI KORFEZI (EGE DENIZI)"},{"date":"2020.11.03","time":"07:56:22","latitude":"37.8238","longitude":"26.8792","depth":"5.7","md":"-.-","ml":"3.3","mw":"3.3","location":"SISAM ADASI (EGE DENIZI)"},{"date":"2020.11.03","time":"07:46:38","latitude":"37.8182","longitude":"27.1288","depth":"18.4","md":"-.-","ml":"1.6","mw":"-.-","location":"KUSADASI KORFEZI (EGE DENIZI)"},{"date":"2020.11.03","time":"07:40:54","latitude":"37.8462","longitude":"26.7383","depth":"4.2","md":"-.-","ml":"2.2","mw":"-.-","location":"EGE DENIZI"},{"date":"2020.11.03","time":"07:40:04","latitude":"37.8413","longitude":"26.6692","depth":"22.3","md":"-.-","ml":"2.1","mw":"-.-","location":"SISAM ADASI (EGE DENIZI)"},{"date":"2020.11.03","time":"07:32:19","latitude":"37.8952","longitude":"26.9718","depth":"8.1","md":"-.-","ml":"2.0","mw":"-.-","location":"KUSADASI KORFEZI (EGE DENIZI)"},{"date":"2020.11.03","time":"07:32:18","latitude":"36.9340","longitude":"27.5168","depth":"15.8","md":"-.-","ml":"1.7","mw":"-.-","location":"GOKOVA KORFEZI (AKDENIZ)"},{"date":"2020.11.03","time":"07:29:11","latitude":"37.7143","longitude":"27.1197","depth":"6.2","md":"-.-","ml":"1.9","mw":"-.-","location":"KUSADASI KORFEZI (EGE DENIZI)"},{"date":"2020.11.03","time":"07:28:05","latitude":"37.7453","longitude":"26.9815","depth":"5.5","md":"-.-","ml":"1.9","mw":"-.-","location":"SISAM ADASI (EGE DENIZI)"},{"date":"2020.11.03","time":"07:25:49","latitude":"37.8485","longitude":"26.7207","depth":"5.4","md":"-.-","ml":"2.2","mw":"-.-","location":"EGE DENIZI"},{"date":"2020.11.03","time":"07:24:55","latitude":"37.6810","longitude":"27.0365","depth":"8.6","md":"-.-","ml":"2.1","mw":"-.-","location":"SISAM ADASI (EGE DENIZI)"},{"date":"2020.11.03","time":"07:22:08","latitude":"37.9172","longitude":"26.9412","depth":"11.7","md":"-.-","ml":"1.8","mw":"-.-","location":"KUSADASI KORFEZI (EGE DENIZI)"},{"date":"2020.11.03","time":"07:21:21","latitude":"37.9118","longitude":"27.0493","depth":"7.8","md":"-.-","ml":"1.8","mw":"-.-","location":"KUSADASI KORFEZI (EGE DENIZI)"},{"date":"2020.11.03","time":"07:16:58","latitude":"37.8488","longitude":"26.9222","depth":"8.6","md":"-.-","ml":"1.8","mw":"-.-","location":"KUSADASI KORFEZI (EGE DENIZI)"},{"date":"2020.11.03","time":"07:08:44","latitude":"37.9133","longitude":"27.0272","depth":"11.3","md":"-.-","ml":"2.1","mw":"-.-","location":"KUSADASI KORFEZI (EGE DENIZI)"},{"date":"2020.11.03","time":"07:06:22","latitude":"37.8735","longitude":"26.7747","depth":"7.9","md":"-.-","ml":"2.4","mw":"-.-","location":"EGE DENIZI"},{"date":"2020.11.03","time":"07:01:32","latitude":"37.8250","longitude":"26.8810","depth":"12.4","md":"-.-","ml":"1.8","mw":"-.-","location":"SISAM ADASI (EGE DENIZI)"},{"date":"2020.11.03","time":"06:59:33","latitude":"37.8640","longitude":"26.4502","depth":"3.9","md":"-.-","ml":"2.5","mw":"-.-","location":"ONIKI ADALAR (AKDENIZ)"},{"date":"2020.11.03","time":"06:47:45","latitude":"37.8365","longitude":"26.3750","depth":"6.6","md":"-.-","ml":"2.4","mw":"-.-","location":"ONIKI ADALAR (AKDENIZ)"},{"date":"2020.11.03","time":"06:44:53","latitude":"37.7435","longitude":"27.3417","depth":"6.5","md":"-.-","ml":"2.1","mw":"-.-","location":"AGACLI-SOKE (AYDIN)"},{"date":"2020.11.03","time":"06:41:49","latitude":"37.6972","longitude":"26.9235","depth":"7.5","md":"-.-","ml":"2.0","mw":"-.-","location":"SISAM ADASI (EGE DENIZI)"},{"date":"2020.11.03","time":"06:39:25","latitude":"38.0668","longitude":"27.1145","depth":"5.3","md":"-.-","ml":"1.7","mw":"-.-","location":"CAMONU-MENDERES (IZMIR)"},{"date":"2020.11.03","time":"06:37:20","latitude":"37.8460","longitude":"26.4242","depth":"8.6","md":"-.-","ml":"1.7","mw":"-.-","location":"ONIKI ADALAR (AKDENIZ)"},{"date":"2020.11.03","time":"06:34:14","latitude":"37.7040","longitude":"26.9782","depth":"5.0","md":"-.-","ml":"3.0","mw":"-.-","location":"SISAM ADASI (EGE DENIZI)"},{"date":"2020.11.03","time":"06:25:07","latitude":"37.5047","longitude":"30.4205","depth":"5.0","md":"-.-","ml":"1.6","mw":"-.-","location":"BAGSARAY-CELTIKCI (BURDUR)"},{"date":"2020.11.03","time":"06:23:26","latitude":"37.6650","longitude":"26.6262","depth":"8.6","md":"-.-","ml":"2.0","mw":"-.-","location":"SISAM ADASI (EGE DENIZI)"},{"date":"2020.11.03","time":"06:21:53","latitude":"37.8862","longitude":"26.4865","depth":"20.7","md":"-.-","ml":"2.0","mw":"-.-","location":"EGE DENIZI"},{"date":"2020.11.03","time":"06:14:50","latitude":"37.8210","longitude":"26.8457","depth":"5.4","md":"-.-","ml":"1.8","mw":"-.-","location":"SISAM ADASI (EGE DENIZI)"},{"date":"2020.11.03","time":"06:13:54","latitude":"37.9195","longitude":"26.4900","depth":"21.5","md":"-.-","ml":"2.0","mw":"-.-","location":"EGE DENIZI"},{"date":"2020.11.03","time":"06:12:02","latitude":"37.8555","longitude":"26.4140","depth":"2.3","md":"-.-","ml":"3.1","mw":"3.1","location":"ONIKI ADALAR (AKDENIZ)"},{"date":"2020.11.03","time":"06:07:16","latitude":"39.3617","longitude":"40.7702","depth":"9.0","md":"-.-","ml":"2.0","mw":"-.-","location":"KAYNARPINAR-KARLIOVA (BINGOL)"},{"date":"2020.11.03","time":"06:03:37","latitude":"37.8173","longitude":"26.8760","depth":"5.0","md":"-.-","ml":"2.6","mw":"-.-","location":"SISAM ADASI (EGE DENIZI)"},{"date":"2020.11.03","time":"05:58:45","latitude":"37.7625","longitude":"27.0360","depth":"13.1","md":"-.-","ml":"1.7","mw":"-.-","location":"KUSADASI KORFEZI (EGE DENIZI)"},{"date":"2020.11.03","time":"05:57:24","latitude":"37.8843","longitude":"26.4523","depth":"7.5","md":"-.-","ml":"2.1","mw":"-.-","location":"EGE DENIZI"},{"date":"2020.11.03","time":"05:52:02","latitude":"37.7355","longitude":"26.9447","depth":"4.8","md":"-.-","ml":"1.9","mw":"-.-","location":"SISAM ADASI (EGE DENIZI)"},{"date":"2020.11.03","time":"05:50:40","latitude":"37.7128","longitude":"27.0128","depth":"5.0","md":"-.-","ml":"1.4","mw":"-.-","location":"SISAM ADASI (EGE DENIZI)"},{"date":"2020.11.03","time":"05:44:46","latitude":"37.8052","longitude":"26.8343","depth":"5.0","md":"-.-","ml":"1.9","mw":"-.-","location":"SISAM ADASI (EGE DENIZI)"},{"date":"2020.11.03","time":"05:42:42","latitude":"37.7715","longitude":"27.0105","depth":"3.2","md":"-.-","ml":"1.5","mw":"-.-","location":"SISAM ADASI (EGE DENIZI)"},{"date":"2020.11.03","time":"05:40:05","latitude":"37.8665","longitude":"26.7218","depth":"5.3","md":"-.-","ml":"2.1","mw":"-.-","location":"EGE DENIZI"},{"date":"2020.11.03","time":"05:32:12","latitude":"37.9230","longitude":"26.6490","depth":"6.2","md":"-.-","ml":"1.9","mw":"-.-","location":"EGE DENIZI"},{"date":"2020.11.03","time":"05:29:03","latitude":"37.9060","longitude":"26.6623","depth":"8.7","md":"-.-","ml":"1.7","mw":"-.-","location":"EGE DENIZI"},{"date":"2020.11.03","time":"05:28:00","latitude":"37.7325","longitude":"27.0153","depth":"5.0","md":"-.-","ml":"1.6","mw":"-.-","location":"SISAM ADASI (EGE DENIZI)"},{"date":"2020.11.03","time":"05:22:46","latitude":"37.8805","longitude":"26.4592","depth":"5.5","md":"-.-","ml":"3.1","mw":"3.1","location":"EGE DENIZI"},{"date":"2020.11.03","time":"05:13:57","latitude":"40.0137","longitude":"24.3827","depth":"4.5","md":"-.-","ml":"1.9","mw":"-.-","location":"YUNANISTAN"},{"date":"2020.11.03","time":"05:12:11","latitude":"37.7498","longitude":"27.0490","depth":"11.3","md":"-.-","ml":"1.7","mw":"-.-","location":"SISAM ADASI (EGE DENIZI)"},{"date":"2020.11.03","time":"05:10:25","latitude":"37.8335","longitude":"26.9307","depth":"6.4","md":"-.-","ml":"1.9","mw":"-.-","location":"KUSADASI KORFEZI (EGE DENIZI)"},{"date":"2020.11.03","time":"04:58:15","latitude":"37.7295","longitude":"27.1622","depth":"7.1","md":"-.-","ml":"1.5","mw":"-.-","location":"KUSADASI KORFEZI (EGE DENIZI)"},{"date":"2020.11.03","time":"04:54:14","latitude":"37.8782","longitude":"26.6118","depth":"8.6","md":"-.-","ml":"1.8","mw":"-.-","location":"EGE DENIZI"},{"date":"2020.11.03","time":"04:53:17","latitude":"37.7777","longitude":"26.8322","depth":"7.4","md":"-.-","ml":"1.8","mw":"-.-","location":"SISAM ADASI (EGE DENIZI)"},{"date":"2020.11.03","time":"04:49:58","latitude":"37.7595","longitude":"26.8763","depth":"7.4","md":"-.-","ml":"1.9","mw":"-.-","location":"SISAM ADASI (EGE DENIZI)"},{"date":"2020.11.03","time":"04:45:35","latitude":"37.8818","longitude":"26.5135","depth":"7.3","md":"-.-","ml":"2.1","mw":"-.-","location":"EGE DENIZI"},{"date":"2020.11.03","time":"04:42:38","latitude":"37.8947","longitude":"26.6953","depth":"8.4","md":"-.-","ml":"2.0","mw":"-.-","location":"EGE DENIZI"},{"date":"2020.11.03","time":"04:38:56","latitude":"37.7187","longitude":"27.1020","depth":"6.0","md":"-.-","ml":"1.5","mw":"-.-","location":"KUSADASI KORFEZI (EGE DENIZI)"},{"date":"2020.11.03","time":"04:32:50","latitude":"37.8465","longitude":"26.4620","depth":"7.5","md":"-.-","ml":"3.2","mw":"3.3","location":"ONIKI ADALAR (AKDENIZ)"},{"date":"2020.11.03","time":"04:28:27","latitude":"37.8557","longitude":"27.0195","depth":"1.6","md":"-.-","ml":"2.3","mw":"-.-","location":"KUSADASI KORFEZI (EGE DENIZI)"},{"date":"2020.11.03","time":"04:27:37","latitude":"37.8737","longitude":"26.8617","depth":"5.7","md":"-.-","ml":"2.3","mw":"-.-","location":"KUSADASI KORFEZI (EGE DENIZI)"},{"date":"2020.11.03","time":"04:23:16","latitude":"37.8568","longitude":"26.9633","depth":"17.3","md":"-.-","ml":"2.2","mw":"-.-","location":"KUSADASI KORFEZI (EGE DENIZI)"},{"date":"2020.11.03","time":"04:22:43","latitude":"37.9350","longitude":"26.9350","depth":"19.8","md":"-.-","ml":"2.3","mw":"-.-","location":"KUSADASI KORFEZI (EGE DENIZI)"},{"date":"2020.11.03","time":"04:20:05","latitude":"37.7983","longitude":"26.7062","depth":"10.3","md":"-.-","ml":"2.1","mw":"-.-","location":"SISAM ADASI (EGE DENIZI)"},{"date":"2020.11.03","time":"04:16:05","latitude":"37.8705","longitude":"26.8540","depth":"4.0","md":"-.-","ml":"1.8","mw":"-.-","location":"KUSADASI KORFEZI (EGE DENIZI)"},{"date":"2020.11.03","time":"04:11:13","latitude":"37.7270","longitude":"27.0402","depth":"5.1","md":"-.-","ml":"1.8","mw":"-.-","location":"SISAM ADASI (EGE DENIZI)"},{"date":"2020.11.03","time":"04:08:37","latitude":"37.6777","longitude":"27.0435","depth":"7.6","md":"-.-","ml":"1.7","mw":"-.-","location":"SISAM ADASI (EGE DENIZI)"},{"date":"2020.11.03","time":"04:07:02","latitude":"37.8472","longitude":"26.4952","depth":"2.8","md":"-.-","ml":"1.9","mw":"-.-","location":"SISAM ADASI (EGE DENIZI)"},{"date":"2020.11.03","time":"04:05:13","latitude":"37.7278","longitude":"27.0003","depth":"11.7","md":"-.-","ml":"2.0","mw":"-.-","location":"SISAM ADASI (EGE DENIZI)"},{"date":"2020.11.03","time":"04:02:10","latitude":"37.8477","longitude":"26.9870","depth":"1.4","md":"-.-","ml":"1.6","mw":"-.-","location":"KUSADASI KORFEZI (EGE DENIZI)"},{"date":"2020.11.03","time":"03:58:10","latitude":"37.9070","longitude":"27.0390","depth":"9.6","md":"-.-","ml":"1.8","mw":"-.-","location":"KUSADASI KORFEZI (EGE DENIZI)"},{"date":"2020.11.03","time":"03:55:39","latitude":"37.8467","longitude":"26.9950","depth":"3.3","md":"-.-","ml":"2.0","mw":"-.-","location":"KUSADASI KORFEZI (EGE DENIZI)"},{"date":"2020.11.03","time":"03:53:41","latitude":"37.9335","longitude":"27.0052","depth":"9.1","md":"-.-","ml":"1.8","mw":"-.-","location":"KUSADASI KORFEZI (EGE DENIZI)"},{"date":"2020.11.03","time":"03:51:20","latitude":"37.8572","longitude":"26.5288","depth":"10.1","md":"-.-","ml":"2.1","mw":"-.-","location":"SISAM ADASI (EGE DENIZI)"},{"date":"2020.11.03","time":"03:48:00","latitude":"37.7238","longitude":"27.0227","depth":"3.4","md":"-.-","ml":"3.2","mw":"3.3","location":"SISAM ADASI (EGE DENIZI)"},{"date":"2020.11.03","time":"03:41:31","latitude":"37.7217","longitude":"26.9718","depth":"5.7","md":"-.-","ml":"1.5","mw":"-.-","location":"SISAM ADASI (EGE DENIZI)"},{"date":"2020.11.03","time":"03:36:52","latitude":"37.8300","longitude":"26.9357","depth":"4.8","md":"-.-","ml":"1.7","mw":"-.-","location":"KUSADASI KORFEZI (EGE DENIZI)"},{"date":"2020.11.03","time":"03:35:22","latitude":"37.9080","longitude":"27.0697","depth":"5.5","md":"-.-","ml":"2.0","mw":"-.-","location":"KUSADASI KORFEZI (EGE DENIZI)"},{"date":"2020.11.03","time":"03:32:45","latitude":"37.7285","longitude":"27.0322","depth":"11.7","md":"-.-","ml":"1.7","mw":"-.-","location":"SISAM ADASI (EGE DENIZI)"},{"date":"2020.11.03","time":"03:27:30","latitude":"37.7435","longitude":"27.0495","depth":"8.5","md":"-.-","ml":"1.3","mw":"-.-","location":"SISAM ADASI (EGE DENIZI)"},{"date":"2020.11.03","time":"03:23:59","latitude":"37.6820","longitude":"27.0393","depth":"3.8","md":"-.-","ml":"1.8","mw":"-.-","location":"SISAM ADASI (EGE DENIZI)"},{"date":"2020.11.03","time":"03:22:38","latitude":"37.8538","longitude":"26.6707","depth":"9.5","md":"-.-","ml":"1.6","mw":"-.-","location":"EGE DENIZI"},{"date":"2020.11.03","time":"03:20:15","latitude":"37.8600","longitude":"26.8438","depth":"5.0","md":"-.-","ml":"1.8","mw":"-.-","location":"EGE DENIZI"},{"date":"2020.11.03","time":"03:17:55","latitude":"37.8593","longitude":"26.4788","depth":"14.2","md":"-.-","ml":"2.1","mw":"-.-","location":"SISAM ADASI (EGE DENIZI)"},{"date":"2020.11.03","time":"03:16:55","latitude":"37.8512","longitude":"26.4013","depth":"5.0","md":"-.-","ml":"2.2","mw":"-.-","location":"ONIKI ADALAR (AKDENIZ)"},{"date":"2020.11.03","time":"03:12:12","latitude":"37.8143","longitude":"26.9038","depth":"9.0","md":"-.-","ml":"2.1","mw":"-.-","location":"SISAM ADASI (EGE DENIZI)"},{"date":"2020.11.03","time":"03:09:38","latitude":"37.7130","longitude":"27.0063","depth":"7.7","md":"-.-","ml":"1.9","mw":"-.-","location":"SISAM ADASI (EGE DENIZI)"},{"date":"2020.11.03","time":"03:06:34","latitude":"37.8488","longitude":"26.9663","depth":"7.5","md":"-.-","ml":"2.4","mw":"-.-","location":"KUSADASI KORFEZI (EGE DENIZI)"},{"date":"2020.11.03","time":"03:03:59","latitude":"37.6972","longitude":"26.9740","depth":"13.1","md":"-.-","ml":"1.9","mw":"-.-","location":"SISAM ADASI (EGE DENIZI)"},{"date":"2020.11.03","time":"03:02:16","latitude":"37.8445","longitude":"26.9245","depth":"5.0","md":"-.-","ml":"2.2","mw":"-.-","location":"KUSADASI KORFEZI (EGE DENIZI)"},{"date":"2020.11.03","time":"03:00:38","latitude":"37.8723","longitude":"26.9915","depth":"3.9","md":"-.-","ml":"2.2","mw":"-.-","location":"KUSADASI KORFEZI (EGE DENIZI)"},{"date":"2020.11.03","time":"02:55:22","latitude":"37.7545","longitude":"26.9978","depth":"3.9","md":"-.-","ml":"1.6","mw":"-.-","location":"SISAM ADASI (EGE DENIZI)"},{"date":"2020.11.03","time":"02:53:10","latitude":"37.9460","longitude":"26.4142","depth":"5.4","md":"-.-","ml":"1.4","mw":"-.-","location":"EGE DENIZI"},{"date":"2020.11.03","time":"02:52:12","latitude":"39.2493","longitude":"38.1597","depth":"1.4","md":"-.-","ml":"1.8","mw":"-.-","location":"BAYIRUSTU-DIVRIGI (SIVAS)"},{"date":"2020.11.03","time":"02:47:25","latitude":"37.8998","longitude":"26.9030","depth":"15.2","md":"-.-","ml":"1.6","mw":"-.-","location":"KUSADASI KORFEZI (EGE DENIZI)"},{"date":"2020.11.03","time":"02:46:38","latitude":"37.8137","longitude":"27.0217","depth":"5.3","md":"-.-","ml":"1.7","mw":"-.-","location":"KUSADASI KORFEZI (EGE DENIZI)"},{"date":"2020.11.03","time":"02:45:28","latitude":"37.8170","longitude":"26.9192","depth":"8.1","md":"-.-","ml":"1.8","mw":"-.-","location":"SISAM ADASI (EGE DENIZI)"},{"date":"2020.11.03","time":"02:40:25","latitude":"37.7502","longitude":"26.9932","depth":"5.0","md":"-.-","ml":"1.7","mw":"-.-","location":"SISAM ADASI (EGE DENIZI)"},{"date":"2020.11.03","time":"02:37:23","latitude":"37.8795","longitude":"26.4860","depth":"6.8","md":"-.-","ml":"2.3","mw":"-.-","location":"EGE DENIZI"},{"date":"2020.11.03","time":"02:34:41","latitude":"37.8368","longitude":"26.3785","depth":"7.7","md":"-.-","ml":"3.0","mw":"3.1","location":"ONIKI ADALAR (AKDENIZ)"},{"date":"2020.11.03","time":"02:33:24","latitude":"37.8903","longitude":"26.9207","depth":"9.1","md":"-.-","ml":"2.1","mw":"-.-","location":"KUSADASI KORFEZI (EGE DENIZI)"},{"date":"2020.11.03","time":"02:32:50","latitude":"37.8687","longitude":"26.7285","depth":"14.0","md":"-.-","ml":"2.4","mw":"-.-","location":"EGE DENIZI"},{"date":"2020.11.03","time":"02:29:09","latitude":"37.8740","longitude":"26.7867","depth":"1.8","md":"-.-","ml":"2.2","mw":"-.-","location":"EGE DENIZI"},{"date":"2020.11.03","time":"02:24:27","latitude":"37.8925","longitude":"26.9092","depth":"5.1","md":"-.-","ml":"1.9","mw":"-.-","location":"KUSADASI KORFEZI (EGE DENIZI)"},{"date":"2020.11.03","time":"02:22:55","latitude":"37.8362","longitude":"26.4870","depth":"9.2","md":"-.-","ml":"1.8","mw":"-.-","location":"SISAM ADASI (EGE DENIZI)"},{"date":"2020.11.03","time":"02:15:35","latitude":"37.7360","longitude":"27.0422","depth":"5.0","md":"-.-","ml":"2.4","mw":"-.-","location":"SISAM ADASI (EGE DENIZI)"},{"date":"2020.11.03","time":"02:12:28","latitude":"37.7887","longitude":"27.0070","depth":"9.6","md":"-.-","ml":"2.0","mw":"-.-","location":"KUSADASI KORFEZI (EGE DENIZI)"},{"date":"2020.11.03","time":"02:11:28","latitude":"37.7523","longitude":"26.9768","depth":"11.2","md":"-.-","ml":"1.7","mw":"-.-","location":"SISAM ADASI (EGE DENIZI)"},{"date":"2020.11.03","time":"02:10:29","latitude":"37.7398","longitude":"27.0825","depth":"2.1","md":"-.-","ml":"1.7","mw":"-.-","location":"KUSADASI KORFEZI (EGE DENIZI)"},{"date":"2020.11.03","time":"02:09:05","latitude":"37.6518","longitude":"26.8767","depth":"6.7","md":"-.-","ml":"2.3","mw":"-.-","location":"EGE DENIZI"},{"date":"2020.11.03","time":"02:02:41","latitude":"37.7560","longitude":"27.0817","depth":"20.0","md":"-.-","ml":"1.8","mw":"-.-","location":"KUSADASI KORFEZI (EGE DENIZI)"},{"date":"2020.11.03","time":"02:02:05","latitude":"37.8802","longitude":"26.8888","depth":"1.7","md":"-.-","ml":"2.2","mw":"-.-","location":"KUSADASI KORFEZI (EGE DENIZI)"},{"date":"2020.11.03","time":"02:00:48","latitude":"37.7503","longitude":"27.0363","depth":"6.5","md":"-.-","ml":"1.9","mw":"-.-","location":"SISAM ADASI (EGE DENIZI)"},{"date":"2020.11.03","time":"01:59:29","latitude":"37.7482","longitude":"26.9980","depth":"4.9","md":"-.-","ml":"1.4","mw":"-.-","location":"SISAM ADASI (EGE DENIZI)"},{"date":"2020.11.03","time":"01:57:14","latitude":"37.7515","longitude":"27.0437","depth":"7.0","md":"-.-","ml":"2.4","mw":"-.-","location":"SISAM ADASI (EGE DENIZI)"},{"date":"2020.11.03","time":"01:55:06","latitude":"37.7538","longitude":"27.0222","depth":"10.2","md":"-.-","ml":"1.4","mw":"-.-","location":"SISAM ADASI (EGE DENIZI)"},{"date":"2020.11.03","time":"01:50:23","latitude":"37.7197","longitude":"27.0152","depth":"4.1","md":"-.-","ml":"1.9","mw":"-.-","location":"SISAM ADASI (EGE DENIZI)"},{"date":"2020.11.03","time":"01:46:16","latitude":"38.0477","longitude":"26.9873","depth":"1.4","md":"-.-","ml":"1.7","mw":"-.-","location":"KUSADASI KORFEZI (EGE DENIZI)"},{"date":"2020.11.03","time":"01:45:10","latitude":"37.7443","longitude":"27.0363","depth":"6.4","md":"-.-","ml":"2.0","mw":"-.-","location":"SISAM ADASI (EGE DENIZI)"},{"date":"2020.11.03","time":"01:37:27","latitude":"37.9202","longitude":"26.9313","depth":"5.5","md":"-.-","ml":"2.1","mw":"-.-","location":"KUSADASI KORFEZI (EGE DENIZI)"},{"date":"2020.11.03","time":"01:35:11","latitude":"37.9113","longitude":"27.0175","depth":"2.8","md":"-.-","ml":"2.1","mw":"-.-","location":"KUSADASI KORFEZI (EGE DENIZI)"},{"date":"2020.11.03","time":"01:34:14","latitude":"37.8292","longitude":"26.9450","depth":"7.8","md":"-.-","ml":"2.1","mw":"-.-","location":"KUSADASI KORFEZI (EGE DENIZI)"},{"date":"2020.11.03","time":"01:31:51","latitude":"37.9207","longitude":"26.9388","depth":"8.9","md":"-.-","ml":"2.2","mw":"-.-","location":"KUSADASI KORFEZI (EGE DENIZI)"},{"date":"2020.11.03","time":"01:23:21","latitude":"38.1688","longitude":"27.2865","depth":"5.6","md":"-.-","ml":"1.8","mw":"-.-","location":"KAPLANCIK-TORBALI (IZMIR)"},{"date":"2020.11.03","time":"01:19:47","latitude":"37.7447","longitude":"27.0393","depth":"5.3","md":"-.-","ml":"1.9","mw":"-.-","location":"SISAM ADASI (EGE DENIZI)"},{"date":"2020.11.03","time":"01:18:05","latitude":"37.7393","longitude":"27.0237","depth":"5.0","md":"-.-","ml":"2.2","mw":"-.-","location":"SISAM ADASI (EGE DENIZI)"},{"date":"2020.11.03","time":"01:09:50","latitude":"37.7465","longitude":"27.0203","depth":"7.5","md":"-.-","ml":"2.2","mw":"-.-","location":"SISAM ADASI (EGE DENIZI)"},{"date":"2020.11.03","time":"01:08:53","latitude":"37.7970","longitude":"26.9003","depth":"5.3","md":"-.-","ml":"1.9","mw":"-.-","location":"SISAM ADASI (EGE DENIZI)"},{"date":"2020.11.03","time":"01:06:44","latitude":"37.7843","longitude":"26.7225","depth":"5.0","md":"-.-","ml":"1.8","mw":"-.-","location":"SISAM ADASI (EGE DENIZI)"},{"date":"2020.11.03","time":"01:00:37","latitude":"37.8377","longitude":"26.8957","depth":"5.4","md":"-.-","ml":"1.9","mw":"-.-","location":"KUSADASI KORFEZI (EGE DENIZI)"},{"date":"2020.11.03","time":"00:59:16","latitude":"37.7533","longitude":"27.1253","depth":"6.2","md":"-.-","ml":"1.9","mw":"-.-","location":"KUSADASI KORFEZI (EGE DENIZI)"},{"date":"2020.11.03","time":"00:53:16","latitude":"37.8695","longitude":"26.5898","depth":"15.9","md":"-.-","ml":"1.7","mw":"-.-","location":"SISAM ADASI (EGE DENIZI)"},{"date":"2020.11.03","time":"00:48:10","latitude":"37.7140","longitude":"26.7105","depth":"5.6","md":"-.-","ml":"1.9","mw":"-.-","location":"SISAM ADASI (EGE DENIZI)"},{"date":"2020.11.03","time":"00:46:57","latitude":"37.8230","longitude":"26.8423","depth":"6.5","md":"-.-","ml":"1.9","mw":"-.-","location":"SISAM ADASI (EGE DENIZI)"},{"date":"2020.11.03","time":"00:44:30","latitude":"37.8902","longitude":"26.8358","depth":"2.4","md":"-.-","ml":"2.0","mw":"-.-","location":"EGE DENIZI"},{"date":"2020.11.03","time":"00:42:54","latitude":"37.8057","longitude":"26.7002","depth":"5.0","md":"-.-","ml":"2.1","mw":"-.-","location":"SISAM ADASI (EGE DENIZI)"},{"date":"2020.11.03","time":"00:42:07","latitude":"37.7497","longitude":"27.0633","depth":"7.4","md":"-.-","ml":"1.9","mw":"-.-","location":"SISAM ADASI (EGE DENIZI)"},{"date":"2020.11.03","time":"00:38:33","latitude":"37.8803","longitude":"26.8888","depth":"5.4","md":"-.-","ml":"2.0","mw":"-.-","location":"KUSADASI KORFEZI (EGE DENIZI)"},{"date":"2020.11.03","time":"00:35:40","latitude":"37.7980","longitude":"26.8342","depth":"6.2","md":"-.-","ml":"1.8","mw":"-.-","location":"SISAM ADASI (EGE DENIZI)"},{"date":"2020.11.03","time":"00:28:31","latitude":"37.8157","longitude":"26.9583","depth":"14.3","md":"-.-","ml":"1.5","mw":"-.-","location":"KUSADASI KORFEZI (EGE DENIZI)"},{"date":"2020.11.03","time":"00:27:47","latitude":"37.9918","longitude":"27.1947","depth":"11.9","md":"-.-","ml":"2.0","mw":"-.-","location":"KUSADASI KORFEZI (EGE DENIZI)"},{"date":"2020.11.03","time":"00:22:59","latitude":"37.8610","longitude":"26.5895","depth":"5.4","md":"-.-","ml":"2.0","mw":"-.-","location":"SISAM ADASI (EGE DENIZI)"},{"date":"2020.11.03","time":"00:20:39","latitude":"37.8460","longitude":"26.8728","depth":"1.3","md":"-.-","ml":"1.8","mw":"-.-","location":"KUSADASI KORFEZI (EGE DENIZI)"},{"date":"2020.11.03","time":"00:17:27","latitude":"37.6980","longitude":"26.9698","depth":"8.6","md":"-.-","ml":"2.4","mw":"-.-","location":"SISAM ADASI (EGE DENIZI)"},{"date":"2020.11.03","time":"00:15:59","latitude":"37.7037","longitude":"27.1070","depth":"10.6","md":"-.-","ml":"2.8","mw":"-.-","location":"KUSADASI KORFEZI (EGE DENIZI)"},{"date":"2020.11.03","time":"00:09:07","latitude":"37.8397","longitude":"26.7477","depth":"7.3","md":"-.-","ml":"2.2","mw":"-.-","location":"EGE DENIZI"},{"date":"2020.11.03","time":"00:08:09","latitude":"37.7273","longitude":"27.0092","depth":"11.0","md":"-.-","ml":"1.9","mw":"-.-","location":"SISAM ADASI (EGE DENIZI)"},{"date":"2020.11.03","time":"00:07:06","latitude":"37.7802","longitude":"26.9965","depth":"3.6","md":"-.-","ml":"2.0","mw":"-.-","location":"KUSADASI KORFEZI (EGE DENIZI)"},{"date":"2020.11.03","time":"00:05:55","latitude":"38.0335","longitude":"26.6848","depth":"3.5","md":"-.-","ml":"2.0","mw":"-.-","location":"EGE DENIZI"},{"date":"2020.11.03","time":"00:03:11","latitude":"37.7535","longitude":"26.9792","depth":"8.4","md":"-.-","ml":"2.1","mw":"-.-","location":"SISAM ADASI (EGE DENIZI)"},{"date":"2020.11.02","time":"23:56:27","latitude":"37.7522","longitude":"27.0248","depth":"5.1","md":"-.-","ml":"2.3","mw":"-.-","location":"SISAM ADASI (EGE DENIZI)"},{"date":"2020.11.02","time":"23:55:29","latitude":"37.7462","longitude":"27.0277","depth":"5.3","md":"-.-","ml":"2.6","mw":"-.-","location":"SISAM ADASI (EGE DENIZI)"},{"date":"2020.11.02","time":"23:51:39","latitude":"37.7155","longitude":"26.9918","depth":"9.3","md":"-.-","ml":"2.9","mw":"-.-","location":"SISAM ADASI (EGE DENIZI)"},{"date":"2020.11.02","time":"23:50:18","latitude":"37.6348","longitude":"26.6623","depth":"10.7","md":"-.-","ml":"1.9","mw":"-.-","location":"SISAM ADASI (EGE DENIZI)"},{"date":"2020.11.02","time":"23:49:21","latitude":"37.7790","longitude":"26.9858","depth":"5.4","md":"-.-","ml":"1.9","mw":"-.-","location":"SISAM ADASI (EGE DENIZI)"},{"date":"2020.11.02","time":"23:43:11","latitude":"37.7165","longitude":"27.0265","depth":"5.3","md":"-.-","ml":"2.5","mw":"-.-","location":"SISAM ADASI (EGE DENIZI)"},{"date":"2020.11.02","time":"23:26:28","latitude":"37.6928","longitude":"27.0907","depth":"5.3","md":"-.-","ml":"2.6","mw":"-.-","location":"KUSADASI KORFEZI (EGE DENIZI)"},{"date":"2020.11.02","time":"23:22:40","latitude":"37.7332","longitude":"26.9992","depth":"10.8","md":"-.-","ml":"1.6","mw":"-.-","location":"SISAM ADASI (EGE DENIZI)"},{"date":"2020.11.02","time":"23:17:19","latitude":"37.5680","longitude":"26.7022","depth":"13.7","md":"-.-","ml":"2.2","mw":"-.-","location":"ONIKI ADALAR (AKDENIZ)"},{"date":"2020.11.02","time":"23:13:02","latitude":"37.7278","longitude":"27.0447","depth":"4.0","md":"-.-","ml":"3.0","mw":"3.2","location":"SISAM ADASI (EGE DENIZI)"},{"date":"2020.11.02","time":"23:10:26","latitude":"37.7197","longitude":"27.0662","depth":"18.0","md":"-.-","ml":"2.0","mw":"-.-","location":"KUSADASI KORFEZI (EGE DENIZI)"},{"date":"2020.11.02","time":"23:03:24","latitude":"37.9470","longitude":"26.8862","depth":"15.3","md":"-.-","ml":"2.9","mw":"-.-","location":"KUSADASI KORFEZI (EGE DENIZI)"},{"date":"2020.11.02","time":"23:02:00","latitude":"37.6405","longitude":"27.1568","depth":"8.7","md":"-.-","ml":"1.7","mw":"-.-","location":"DOGANBEY-SOKE (AYDIN)"},{"date":"2020.11.02","time":"22:59:49","latitude":"37.9048","longitude":"26.6660","depth":"12.5","md":"-.-","ml":"2.1","mw":"-.-","location":"EGE DENIZI"},{"date":"2020.11.02","time":"22:48:47","latitude":"37.8270","longitude":"26.4550","depth":"5.4","md":"-.-","ml":"3.0","mw":"-.-","location":"ONIKI ADALAR (AKDENIZ)"},{"date":"2020.11.02","time":"22:46:35","latitude":"37.7417","longitude":"27.0522","depth":"11.3","md":"-.-","ml":"3.0","mw":"-.-","location":"SISAM ADASI (EGE DENIZI)"},{"date":"2020.11.02","time":"22:42:06","latitude":"37.7057","longitude":"26.8963","depth":"8.0","md":"-.-","ml":"2.1","mw":"-.-","location":"SISAM ADASI (EGE DENIZI)"},{"date":"2020.11.02","time":"22:39:12","latitude":"37.7242","longitude":"27.0525","depth":"11.1","md":"-.-","ml":"3.7","mw":"3.8","location":"SISAM ADASI (EGE DENIZI)"},{"date":"2020.11.02","time":"22:35:06","latitude":"37.7800","longitude":"27.2035","depth":"24.0","md":"-.-","ml":"1.6","mw":"-.-","location":"KUSADASI KORFEZI (EGE DENIZI)"},{"date":"2020.11.02","time":"22:23:21","latitude":"37.8612","longitude":"27.0160","depth":"14.6","md":"-.-","ml":"1.8","mw":"-.-","location":"KUSADASI KORFEZI (EGE DENIZI)"},{"date":"2020.11.02","time":"22:22:08","latitude":"37.8768","longitude":"26.9122","depth":"12.1","md":"-.-","ml":"2.4","mw":"-.-","location":"KUSADASI KORFEZI (EGE DENIZI)"},{"date":"2020.11.02","time":"22:21:20","latitude":"37.8417","longitude":"26.7363","depth":"5.0","md":"-.-","ml":"2.3","mw":"-.-","location":"EGE DENIZI"},{"date":"2020.11.02","time":"22:16:41","latitude":"37.8802","longitude":"26.5118","depth":"7.0","md":"-.-","ml":"4.2","mw":"4.1","location":"EGE DENIZI"},{"date":"2020.11.02","time":"22:14:49","latitude":"37.7167","longitude":"26.9990","depth":"12.2","md":"-.-","ml":"1.7","mw":"-.-","location":"SISAM ADASI (EGE DENIZI)"},{"date":"2020.11.02","time":"22:12:37","latitude":"37.8278","longitude":"26.8707","depth":"13.5","md":"-.-","ml":"1.9","mw":"-.-","location":"SISAM ADASI (EGE DENIZI)"},{"date":"2020.11.02","time":"22:10:21","latitude":"37.7658","longitude":"27.0500","depth":"18.0","md":"-.-","ml":"1.8","mw":"-.-","location":"KUSADASI KORFEZI (EGE DENIZI)"},{"date":"2020.11.02","time":"22:09:16","latitude":"37.7342","longitude":"27.0300","depth":"2.9","md":"-.-","ml":"2.0","mw":"-.-","location":"SISAM ADASI (EGE DENIZI)"},{"date":"2020.11.02","time":"22:08:32","latitude":"37.8258","longitude":"26.8860","depth":"14.9","md":"-.-","ml":"2.1","mw":"-.-","location":"SISAM ADASI (EGE DENIZI)"},{"date":"2020.11.02","time":"22:05:44","latitude":"37.7037","longitude":"27.0333","depth":"13.4","md":"-.-","ml":"2.3","mw":"-.-","location":"SISAM ADASI (EGE DENIZI)"},{"date":"2020.11.02","time":"22:04:00","latitude":"37.7183","longitude":"27.0865","depth":"5.0","md":"-.-","ml":"2.2","mw":"-.-","location":"KUSADASI KORFEZI (EGE DENIZI)"},{"date":"2020.11.02","time":"21:59:33","latitude":"37.7215","longitude":"27.1092","depth":"10.8","md":"-.-","ml":"2.8","mw":"-.-","location":"KUSADASI KORFEZI (EGE DENIZI)"},{"date":"2020.11.02","time":"21:56:10","latitude":"37.7422","longitude":"27.1107","depth":"2.6","md":"-.-","ml":"1.8","mw":"-.-","location":"KUSADASI KORFEZI (EGE DENIZI)"},{"date":"2020.11.02","time":"21:55:44","latitude":"37.8610","longitude":"26.8367","depth":"11.6","md":"-.-","ml":"2.2","mw":"-.-","location":"EGE DENIZI"},{"date":"2020.11.02","time":"21:52:18","latitude":"37.8862","longitude":"26.9785","depth":"16.1","md":"-.-","ml":"1.6","mw":"-.-","location":"KUSADASI KORFEZI (EGE DENIZI)"},{"date":"2020.11.02","time":"21:50:42","latitude":"37.8703","longitude":"26.6387","depth":"9.9","md":"-.-","ml":"2.2","mw":"-.-","location":"EGE DENIZI"},{"date":"2020.11.02","time":"21:48:30","latitude":"37.8610","longitude":"26.4908","depth":"9.5","md":"-.-","ml":"2.5","mw":"-.-","location":"SISAM ADASI (EGE DENIZI)"},{"date":"2020.11.02","time":"21:47:25","latitude":"37.8243","longitude":"26.6847","depth":"13.7","md":"-.-","ml":"1.7","mw":"-.-","location":"SISAM ADASI (EGE DENIZI)"},{"date":"2020.11.02","time":"21:43:05","latitude":"37.8552","longitude":"26.9102","depth":"5.5","md":"-.-","ml":"1.9","mw":"-.-","location":"KUSADASI KORFEZI (EGE DENIZI)"},{"date":"2020.11.02","time":"21:42:09","latitude":"37.7055","longitude":"27.1345","depth":"10.1","md":"-.-","ml":"1.8","mw":"-.-","location":"KUSADASI KORFEZI (EGE DENIZI)"},{"date":"2020.11.02","time":"21:41:27","latitude":"37.7102","longitude":"27.0972","depth":"16.7","md":"-.-","ml":"2.2","mw":"-.-","location":"KUSADASI KORFEZI (EGE DENIZI)"},{"date":"2020.11.02","time":"21:36:40","latitude":"37.9022","longitude":"26.8480","depth":"20.5","md":"-.-","ml":"1.9","mw":"-.-","location":"KUSADASI KORFEZI (EGE DENIZI)"},{"date":"2020.11.02","time":"21:35:05","latitude":"37.8533","longitude":"27.2050","depth":"5.0","md":"-.-","ml":"2.3","mw":"-.-","location":"KUSADASI KORFEZI (EGE DENIZI)"},{"date":"2020.11.02","time":"21:31:10","latitude":"37.9415","longitude":"27.1153","depth":"11.6","md":"-.-","ml":"3.2","mw":"-.-","location":"KUSADASI KORFEZI (EGE DENIZI)"},{"date":"2020.11.02","time":"21:28:17","latitude":"37.6457","longitude":"26.5900","depth":"5.0","md":"-.-","ml":"2.0","mw":"-.-","location":"SISAM ADASI (EGE DENIZI)"},{"date":"2020.11.02","time":"21:24:48","latitude":"37.8428","longitude":"26.9927","depth":"11.0","md":"-.-","ml":"2.4","mw":"-.-","location":"KUSADASI KORFEZI (EGE DENIZI)"},{"date":"2020.11.02","time":"21:22:13","latitude":"36.8077","longitude":"31.8687","depth":"2.9","md":"-.-","ml":"3.0","mw":"-.-","location":"CICEKOLUK-GUNDOGMUS (ANTALYA)"},{"date":"2020.11.02","time":"21:20:16","latitude":"37.7388","longitude":"27.0467","depth":"5.1","md":"-.-","ml":"1.8","mw":"-.-","location":"SISAM ADASI (EGE DENIZI)"},{"date":"2020.11.02","time":"21:12:17","latitude":"37.8725","longitude":"26.9290","depth":"9.7","md":"-.-","ml":"2.3","mw":"-.-","location":"KUSADASI KORFEZI (EGE DENIZI)"},{"date":"2020.11.02","time":"21:11:17","latitude":"37.8090","longitude":"27.0097","depth":"8.9","md":"-.-","ml":"2.0","mw":"-.-","location":"KUSADASI KORFEZI (EGE DENIZI)"},{"date":"2020.11.02","time":"20:56:24","latitude":"37.5132","longitude":"30.4207","depth":"5.0","md":"-.-","ml":"2.9","mw":"-.-","location":"BAGSARAY-CELTIKCI (BURDUR)"},{"date":"2020.11.02","time":"20:50:21","latitude":"37.8475","longitude":"26.9377","depth":"5.7","md":"-.-","ml":"2.1","mw":"-.-","location":"KUSADASI KORFEZI (EGE DENIZI)"},{"date":"2020.11.02","time":"20:49:42","latitude":"37.8698","longitude":"26.9058","depth":"10.0","md":"-.-","ml":"2.5","mw":"-.-","location":"KUSADASI KORFEZI (EGE DENIZI)"},{"date":"2020.11.02","time":"20:48:48","latitude":"37.8173","longitude":"26.8633","depth":"14.6","md":"-.-","ml":"2.1","mw":"-.-","location":"SISAM ADASI (EGE DENIZI)"},{"date":"2020.11.02","time":"20:47:35","latitude":"37.7648","longitude":"27.0477","depth":"4.0","md":"-.-","ml":"2.2","mw":"-.-","location":"KUSADASI KORFEZI (EGE DENIZI)"},{"date":"2020.11.02","time":"20:47:08","latitude":"37.7355","longitude":"27.0745","depth":"16.1","md":"-.-","ml":"2.2","mw":"-.-","location":"KUSADASI KORFEZI (EGE DENIZI)"},{"date":"2020.11.02","time":"20:43:47","latitude":"37.8142","longitude":"27.0643","depth":"4.6","md":"-.-","ml":"2.5","mw":"-.-","location":"KUSADASI KORFEZI (EGE DENIZI)"},{"date":"2020.11.02","time":"20:43:10","latitude":"37.8405","longitude":"26.4760","depth":"6.2","md":"-.-","ml":"3.4","mw":"3.5","location":"SISAM ADASI (EGE DENIZI)"},{"date":"2020.11.02","time":"20:42:00","latitude":"37.7498","longitude":"27.0555","depth":"13.6","md":"-.-","ml":"2.7","mw":"-.-","location":"SISAM ADASI (EGE DENIZI)"},{"date":"2020.11.02","time":"20:36:57","latitude":"37.6430","longitude":"27.0410","depth":"5.0","md":"-.-","ml":"2.2","mw":"-.-","location":"DOGANBEY ACIKLARI-AYDIN (EGE DENIZI)"},{"date":"2020.11.02","time":"20:34:22","latitude":"37.9035","longitude":"26.6627","depth":"8.6","md":"-.-","ml":"2.0","mw":"-.-","location":"EGE DENIZI"},{"date":"2020.11.02","time":"20:30:30","latitude":"37.7170","longitude":"27.0118","depth":"8.6","md":"-.-","ml":"2.6","mw":"-.-","location":"SISAM ADASI (EGE DENIZI)"},{"date":"2020.11.02","time":"20:29:45","latitude":"37.7442","longitude":"27.0903","depth":"5.1","md":"-.-","ml":"1.6","mw":"-.-","location":"KUSADASI KORFEZI (EGE DENIZI)"},{"date":"2020.11.02","time":"20:28:00","latitude":"38.0042","longitude":"26.8763","depth":"13.3","md":"-.-","ml":"2.0","mw":"-.-","location":"KUSADASI KORFEZI (EGE DENIZI)"},{"date":"2020.11.02","time":"20:25:53","latitude":"37.7375","longitude":"27.0132","depth":"17.1","md":"-.-","ml":"2.0","mw":"-.-","location":"SISAM ADASI (EGE DENIZI)"},{"date":"2020.11.02","time":"20:21:59","latitude":"37.7178","longitude":"27.0957","depth":"15.0","md":"-.-","ml":"2.1","mw":"-.-","location":"KUSADASI KORFEZI (EGE DENIZI)"},{"date":"2020.11.02","time":"20:21:15","latitude":"37.6813","longitude":"26.9602","depth":"5.5","md":"-.-","ml":"2.5","mw":"-.-","location":"SISAM ADASI (EGE DENIZI)"},{"date":"2020.11.02","time":"20:10:41","latitude":"37.8570","longitude":"27.2517","depth":"7.6","md":"-.-","ml":"2.1","mw":"-.-","location":"KUSADASI (AYDIN)"},{"date":"2020.11.02","time":"20:05:42","latitude":"37.8302","longitude":"26.8223","depth":"4.4","md":"-.-","ml":"3.6","mw":"3.6","location":"SISAM ADASI (EGE DENIZI)"},{"date":"2020.11.02","time":"19:49:49","latitude":"37.7173","longitude":"26.9952","depth":"4.3","md":"-.-","ml":"1.9","mw":"-.-","location":"SISAM ADASI (EGE DENIZI)"},{"date":"2020.11.02","time":"19:45:36","latitude":"37.7183","longitude":"27.0063","depth":"3.3","md":"-.-","ml":"2.0","mw":"-.-","location":"SISAM ADASI (EGE DENIZI)"},{"date":"2020.11.02","time":"19:41:45","latitude":"37.7412","longitude":"27.1377","depth":"9.8","md":"-.-","ml":"2.6","mw":"-.-","location":"KUSADASI KORFEZI (EGE DENIZI)"},{"date":"2020.11.02","time":"19:39:13","latitude":"37.7362","longitude":"27.0350","depth":"8.4","md":"-.-","ml":"3.5","mw":"3.6","location":"SISAM ADASI (EGE DENIZI)"},{"date":"2020.11.02","time":"19:35:15","latitude":"37.7115","longitude":"27.0885","depth":"7.7","md":"-.-","ml":"2.6","mw":"-.-","location":"KUSADASI KORFEZI (EGE DENIZI)"},{"date":"2020.11.02","time":"19:32:00","latitude":"37.7148","longitude":"27.0102","depth":"12.7","md":"-.-","ml":"3.0","mw":"3.1","location":"SISAM ADASI (EGE DENIZI)"},{"date":"2020.11.02","time":"19:28:17","latitude":"37.7265","longitude":"27.0690","depth":"9.1","md":"-.-","ml":"2.2","mw":"-.-","location":"KUSADASI KORFEZI (EGE DENIZI)"},{"date":"2020.11.02","time":"19:23:47","latitude":"36.6092","longitude":"28.7908","depth":"7.7","md":"-.-","ml":"1.6","mw":"-.-","location":"DALAMAN ACIKLARI-MUGLA (AKDENIZ)"},{"date":"2020.11.02","time":"19:08:54","latitude":"37.6520","longitude":"26.9200","depth":"14.4","md":"-.-","ml":"2.0","mw":"-.-","location":"EGE DENIZI"},{"date":"2020.11.02","time":"19:07:26","latitude":"37.8505","longitude":"26.8803","depth":"9.1","md":"-.-","ml":"2.3","mw":"-.-","location":"KUSADASI KORFEZI (EGE DENIZI)"},{"date":"2020.11.02","time":"19:06:07","latitude":"37.6533","longitude":"27.0400","depth":"12.2","md":"-.-","ml":"2.3","mw":"-.-","location":"DOGANBEY ACIKLARI-AYDIN (EGE DENIZI)"},{"date":"2020.11.02","time":"19:02:07","latitude":"34.0292","longitude":"32.3262","depth":"75.9","md":"-.-","ml":"3.2","mw":"3.3","location":"KIBRIS RUM KESIMI"},{"date":"2020.11.02","time":"18:54:05","latitude":"37.7967","longitude":"27.0188","depth":"5.3","md":"-.-","ml":"2.6","mw":"-.-","location":"KUSADASI KORFEZI (EGE DENIZI)"},{"date":"2020.11.02","time":"18:52:50","latitude":"37.8893","longitude":"26.9608","depth":"5.7","md":"-.-","ml":"2.4","mw":"-.-","location":"KUSADASI KORFEZI (EGE DENIZI)"},{"date":"2020.11.02","time":"18:51:32","latitude":"37.9102","longitude":"26.8972","depth":"18.8","md":"-.-","ml":"2.3","mw":"-.-","location":"KUSADASI KORFEZI (EGE DENIZI)"},{"date":"2020.11.02","time":"18:50:40","latitude":"37.7150","longitude":"26.9427","depth":"5.0","md":"-.-","ml":"2.1","mw":"-.-","location":"SISAM ADASI (EGE DENIZI)"},{"date":"2020.11.02","time":"18:50:17","latitude":"36.2525","longitude":"28.9525","depth":"10.3","md":"-.-","ml":"1.5","mw":"-.-","location":"AKDENIZ"},{"date":"2020.11.02","time":"18:46:49","latitude":"37.8420","longitude":"26.8422","depth":"9.7","md":"-.-","ml":"2.7","mw":"-.-","location":"SISAM ADASI (EGE DENIZI)"},{"date":"2020.11.02","time":"18:43:01","latitude":"37.7983","longitude":"27.0505","depth":"16.8","md":"-.-","ml":"2.3","mw":"-.-","location":"KUSADASI KORFEZI (EGE DENIZI)"},{"date":"2020.11.02","time":"18:37:30","latitude":"37.6367","longitude":"26.9688","depth":"7.2","md":"-.-","ml":"3.3","mw":"-.-","location":"DOGANBEY ACIKLARI-AYDIN (EGE DENIZI)"},{"date":"2020.11.02","time":"18:34:53","latitude":"37.7098","longitude":"27.0415","depth":"11.4","md":"-.-","ml":"2.5","mw":"-.-","location":"SISAM ADASI (EGE DENIZI)"},{"date":"2020.11.02","time":"18:27:11","latitude":"37.7473","longitude":"27.0435","depth":"7.6","md":"-.-","ml":"2.7","mw":"-.-","location":"SISAM ADASI (EGE DENIZI)"},{"date":"2020.11.02","time":"18:24:05","latitude":"37.7215","longitude":"27.0598","depth":"23.5","md":"-.-","ml":"2.3","mw":"-.-","location":"SISAM ADASI (EGE DENIZI)"},{"date":"2020.11.02","time":"18:22:28","latitude":"37.7705","longitude":"26.6710","depth":"8.6","md":"-.-","ml":"2.6","mw":"-.-","location":"SISAM ADASI (EGE DENIZI)"},{"date":"2020.11.02","time":"18:21:12","latitude":"37.7338","longitude":"27.0368","depth":"3.5","md":"-.-","ml":"2.2","mw":"-.-","location":"SISAM ADASI (EGE DENIZI)"},{"date":"2020.11.02","time":"18:19:03","latitude":"37.7627","longitude":"27.0442","depth":"2.0","md":"-.-","ml":"2.1","mw":"-.-","location":"KUSADASI KORFEZI (EGE DENIZI)"},{"date":"2020.11.02","time":"18:15:05","latitude":"37.7018","longitude":"27.0070","depth":"12.0","md":"-.-","ml":"3.3","mw":"3.5","location":"SISAM ADASI (EGE DENIZI)"},{"date":"2020.11.02","time":"18:13:23","latitude":"37.7465","longitude":"27.0847","depth":"5.3","md":"-.-","ml":"2.8","mw":"-.-","location":"KUSADASI KORFEZI (EGE DENIZI)"},{"date":"2020.11.02","time":"18:09:07","latitude":"37.7258","longitude":"27.0428","depth":"5.3","md":"-.-","ml":"3.9","mw":"3.9","location":"SISAM ADASI (EGE DENIZI)"},{"date":"2020.11.02","time":"18:00:33","latitude":"37.7190","longitude":"27.0203","depth":"10.2","md":"-.-","ml":"2.8","mw":"-.-","location":"SISAM ADASI (EGE DENIZI)"},{"date":"2020.11.02","time":"17:59:34","latitude":"37.7288","longitude":"27.0515","depth":"11.9","md":"-.-","ml":"3.2","mw":"3.4","location":"SISAM ADASI (EGE DENIZI)"},{"date":"2020.11.02","time":"17:58:37","latitude":"37.7298","longitude":"27.0330","depth":"7.2","md":"-.-","ml":"2.9","mw":"-.-","location":"SISAM ADASI (EGE DENIZI)"},{"date":"2020.11.02","time":"17:57:10","latitude":"37.8707","longitude":"27.0090","depth":"2.7","md":"-.-","ml":"2.9","mw":"-.-","location":"KUSADASI KORFEZI (EGE DENIZI)"},{"date":"2020.11.02","time":"17:54:03","latitude":"37.7247","longitude":"27.0378","depth":"9.9","md":"-.-","ml":"3.6","mw":"3.7","location":"SISAM ADASI (EGE DENIZI)"},{"date":"2020.11.02","time":"17:53:10","latitude":"37.7362","longitude":"27.0368","depth":"6.3","md":"-.-","ml":"3.4","mw":"-.-","location":"SISAM ADASI (EGE DENIZI)"},{"date":"2020.11.02","time":"17:46:27","latitude":"37.7852","longitude":"26.6310","depth":"15.2","md":"-.-","ml":"2.6","mw":"-.-","location":"SISAM ADASI (EGE DENIZI)"},{"date":"2020.11.02","time":"17:41:49","latitude":"37.7327","longitude":"27.0405","depth":"7.7","md":"-.-","ml":"2.6","mw":"-.-","location":"SISAM ADASI (EGE DENIZI)"},{"date":"2020.11.02","time":"17:39:54","latitude":"37.8170","longitude":"27.0827","depth":"10.3","md":"-.-","ml":"1.6","mw":"-.-","location":"KUSADASI KORFEZI (EGE DENIZI)"},{"date":"2020.11.02","time":"17:38:40","latitude":"37.8098","longitude":"26.7143","depth":"15.4","md":"-.-","ml":"2.1","mw":"-.-","location":"SISAM ADASI (EGE DENIZI)"},{"date":"2020.11.02","time":"17:25:12","latitude":"37.8772","longitude":"26.9938","depth":"7.3","md":"-.-","ml":"2.0","mw":"-.-","location":"KUSADASI KORFEZI (EGE DENIZI)"},{"date":"2020.11.02","time":"17:19:44","latitude":"37.9013","longitude":"27.0910","depth":"3.1","md":"-.-","ml":"1.9","mw":"-.-","location":"KUSADASI KORFEZI (EGE DENIZI)"},{"date":"2020.11.02","time":"17:19:20","latitude":"37.6988","longitude":"27.1128","depth":"9.2","md":"-.-","ml":"2.2","mw":"-.-","location":"KUSADASI KORFEZI (EGE DENIZI)"},{"date":"2020.11.02","time":"17:12:18","latitude":"37.7163","longitude":"27.0677","depth":"3.6","md":"-.-","ml":"3.0","mw":"3.2","location":"KUSADASI KORFEZI (EGE DENIZI)"},{"date":"2020.11.02","time":"17:07:31","latitude":"37.7068","longitude":"27.1140","depth":"6.6","md":"-.-","ml":"2.3","mw":"-.-","location":"KUSADASI KORFEZI (EGE DENIZI)"},{"date":"2020.11.02","time":"17:05:31","latitude":"37.8160","longitude":"26.7623","depth":"3.6","md":"-.-","ml":"2.1","mw":"-.-","location":"EGE DENIZI"},{"date":"2020.11.02","time":"16:57:12","latitude":"37.9092","longitude":"26.5090","depth":"1.2","md":"-.-","ml":"2.4","mw":"-.-","location":"EGE DENIZI"},{"date":"2020.11.02","time":"16:52:45","latitude":"37.9030","longitude":"26.4913","depth":"5.0","md":"-.-","ml":"2.3","mw":"-.-","location":"EGE DENIZI"},{"date":"2020.11.02","time":"16:49:16","latitude":"37.9735","longitude":"27.2347","depth":"15.4","md":"-.-","ml":"1.8","mw":"-.-","location":"ZEYTINKOY-SELCUK (IZMIR)"},{"date":"2020.11.02","time":"16:40:25","latitude":"37.7777","longitude":"26.9907","depth":"8.0","md":"-.-","ml":"1.7","mw":"-.-","location":"SISAM ADASI (EGE DENIZI)"},{"date":"2020.11.02","time":"16:33:46","latitude":"37.8240","longitude":"26.7492","depth":"5.0","md":"-.-","ml":"2.7","mw":"-.-","location":"EGE DENIZI"},{"date":"2020.11.02","time":"16:27:53","latitude":"38.9935","longitude":"25.7087","depth":"4.8","md":"-.-","ml":"2.6","mw":"-.-","location":"EGE DENIZI"},{"date":"2020.11.02","time":"16:25:35","latitude":"37.8688","longitude":"26.9442","depth":"5.0","md":"-.-","ml":"2.3","mw":"-.-","location":"KUSADASI KORFEZI (EGE DENIZI)"},{"date":"2020.11.02","time":"16:23:50","latitude":"37.8672","longitude":"26.8305","depth":"5.1","md":"-.-","ml":"2.1","mw":"-.-","location":"EGE DENIZI"},{"date":"2020.11.02","time":"16:22:21","latitude":"37.8442","longitude":"26.9448","depth":"4.9","md":"-.-","ml":"1.7","mw":"-.-","location":"KUSADASI KORFEZI (EGE DENIZI)"},{"date":"2020.11.02","time":"16:21:14","latitude":"37.7522","longitude":"26.8580","depth":"5.0","md":"-.-","ml":"1.5","mw":"-.-","location":"SISAM ADASI (EGE DENIZI)"},{"date":"2020.11.02","time":"16:19:32","latitude":"37.7950","longitude":"26.7363","depth":"3.0","md":"-.-","ml":"2.6","mw":"-.-","location":"SISAM ADASI (EGE DENIZI)"},{"date":"2020.11.02","time":"16:14:18","latitude":"37.9047","longitude":"26.9673","depth":"5.2","md":"-.-","ml":"2.2","mw":"-.-","location":"KUSADASI KORFEZI (EGE DENIZI)"},{"date":"2020.11.02","time":"16:12:36","latitude":"37.8873","longitude":"27.0130","depth":"4.7","md":"-.-","ml":"1.9","mw":"-.-","location":"KUSADASI KORFEZI (EGE DENIZI)"},{"date":"2020.11.02","time":"16:08:35","latitude":"37.9192","longitude":"26.7147","depth":"5.2","md":"-.-","ml":"2.0","mw":"-.-","location":"EGE DENIZI"},{"date":"2020.11.02","time":"16:02:34","latitude":"37.9125","longitude":"26.9497","depth":"19.3","md":"-.-","ml":"1.8","mw":"-.-","location":"KUSADASI KORFEZI (EGE DENIZI)"},{"date":"2020.11.02","time":"15:57:01","latitude":"37.8245","longitude":"26.7578","depth":"5.0","md":"-.-","ml":"2.1","mw":"-.-","location":"EGE DENIZI"},{"date":"2020.11.02","time":"15:49:50","latitude":"38.4712","longitude":"26.0420","depth":"5.0","md":"-.-","ml":"1.9","mw":"-.-","location":"SAKIZ ADASI (EGE DENIZI)"},{"date":"2020.11.02","time":"15:38:34","latitude":"37.7825","longitude":"26.4197","depth":"8.4","md":"-.-","ml":"2.7","mw":"-.-","location":"ONIKI ADALAR (AKDENIZ)"},{"date":"2020.11.02","time":"15:30:39","latitude":"37.8322","longitude":"26.7137","depth":"7.2","md":"-.-","ml":"3.7","mw":"-.-","location":"EGE DENIZI"},{"date":"2020.11.02","time":"15:26:35","latitude":"37.7408","longitude":"27.0317","depth":"5.0","md":"-.-","ml":"2.8","mw":"-.-","location":"SISAM ADASI (EGE DENIZI)"},{"date":"2020.11.02","time":"15:20:54","latitude":"37.8532","longitude":"26.8382","depth":"4.1","md":"-.-","ml":"2.5","mw":"-.-","location":"EGE DENIZI"},{"date":"2020.11.02","time":"15:17:20","latitude":"37.8062","longitude":"26.7923","depth":"7.4","md":"-.-","ml":"3.1","mw":"3.0","location":"SISAM ADASI (EGE DENIZI)"},{"date":"2020.11.02","time":"15:11:51","latitude":"36.0320","longitude":"27.6922","depth":"26.3","md":"-.-","ml":"3.4","mw":"-.-","location":"AKDENIZ"},{"date":"2020.11.02","time":"14:58:03","latitude":"37.8758","longitude":"26.9102","depth":"8.0","md":"-.-","ml":"4.4","mw":"-.-","location":"KUSADASI KORFEZI (EGE DENIZI)"},{"date":"2020.11.02","time":"14:50:24","latitude":"39.0012","longitude":"27.5797","depth":"5.8","md":"-.-","ml":"2.5","mw":"-.-","location":"SULEYMANKOY-AKHISAR (MANISA)"},{"date":"2020.11.02","time":"14:44:16","latitude":"37.8900","longitude":"26.8515","depth":"20.7","md":"-.-","ml":"1.8","mw":"-.-","location":"KUSADASI KORFEZI (EGE DENIZI)"},{"date":"2020.11.02","time":"14:40:27","latitude":"37.8962","longitude":"26.8920","depth":"18.7","md":"-.-","ml":"2.1","mw":"-.-","location":"KUSADASI KORFEZI (EGE DENIZI)"},{"date":"2020.11.02","time":"14:35:46","latitude":"37.8893","longitude":"26.6347","depth":"5.6","md":"-.-","ml":"2.6","mw":"-.-","location":"EGE DENIZI"},{"date":"2020.11.02","time":"14:34:59","latitude":"37.8620","longitude":"26.8002","depth":"6.5","md":"-.-","ml":"2.3","mw":"-.-","location":"EGE DENIZI"},{"date":"2020.11.02","time":"14:30:39","latitude":"37.8868","longitude":"27.0092","depth":"5.4","md":"-.-","ml":"2.1","mw":"-.-","location":"KUSADASI KORFEZI (EGE DENIZI)"},{"date":"2020.11.02","time":"14:28:31","latitude":"37.9002","longitude":"26.9252","depth":"8.7","md":"-.-","ml":"2.2","mw":"-.-","location":"KUSADASI KORFEZI (EGE DENIZI)"},{"date":"2020.11.02","time":"14:23:56","latitude":"37.8952","longitude":"26.8377","depth":"7.9","md":"-.-","ml":"2.1","mw":"-.-","location":"KUSADASI KORFEZI (EGE DENIZI)"},{"date":"2020.11.02","time":"14:15:28","latitude":"37.7460","longitude":"27.0817","depth":"10.6","md":"-.-","ml":"2.0","mw":"-.-","location":"KUSADASI KORFEZI (EGE DENIZI)"},{"date":"2020.11.02","time":"14:13:46","latitude":"37.8302","longitude":"26.9803","depth":"12.5","md":"-.-","ml":"2.2","mw":"-.-","location":"KUSADASI KORFEZI (EGE DENIZI)"},{"date":"2020.11.02","time":"13:57:36","latitude":"37.9448","longitude":"27.1610","depth":"12.1","md":"-.-","ml":"2.4","mw":"-.-","location":"KUSADASI KORFEZI (EGE DENIZI)"},{"date":"2020.11.02","time":"13:55:59","latitude":"37.8285","longitude":"26.7412","depth":"5.2","md":"-.-","ml":"2.2","mw":"-.-","location":"EGE DENIZI"},{"date":"2020.11.02","time":"13:51:22","latitude":"37.8440","longitude":"26.6305","depth":"5.4","md":"-.-","ml":"2.0","mw":"-.-","location":"SISAM ADASI (EGE DENIZI)"},{"date":"2020.11.02","time":"13:45:14","latitude":"38.9240","longitude":"27.0872","depth":"8.8","md":"-.-","ml":"1.9","mw":"-.-","location":"ASAGISAKRAN-ALIAGA (IZMIR)"},{"date":"2020.11.02","time":"13:41:29","latitude":"37.8265","longitude":"26.9238","depth":"7.3","md":"-.-","ml":"2.2","mw":"-.-","location":"KUSADASI KORFEZI (EGE DENIZI)"},{"date":"2020.11.02","time":"13:37:57","latitude":"37.8645","longitude":"26.8655","depth":"7.7","md":"-.-","ml":"2.5","mw":"-.-","location":"KUSADASI KORFEZI (EGE DENIZI)"},{"date":"2020.11.02","time":"13:34:32","latitude":"37.7357","longitude":"27.0497","depth":"7.0","md":"-.-","ml":"1.8","mw":"-.-","location":"SISAM ADASI (EGE DENIZI)"},{"date":"2020.11.02","time":"13:31:55","latitude":"38.0510","longitude":"27.2783","depth":"5.3","md":"-.-","ml":"2.6","mw":"-.-","location":"GOLOVA-MENDERES (IZMIR)"},{"date":"2020.11.02","time":"13:30:30","latitude":"37.7250","longitude":"27.1465","depth":"5.8","md":"-.-","ml":"2.2","mw":"-.-","location":"KUSADASI KORFEZI (EGE DENIZI)"},{"date":"2020.11.02","time":"13:24:13","latitude":"37.8618","longitude":"26.6660","depth":"4.6","md":"-.-","ml":"1.9","mw":"-.-","location":"EGE DENIZI"},{"date":"2020.11.02","time":"13:14:54","latitude":"37.8455","longitude":"26.4730","depth":"7.0","md":"-.-","ml":"2.3","mw":"-.-","location":"SISAM ADASI (EGE DENIZI)"},{"date":"2020.11.02","time":"13:02:41","latitude":"37.8383","longitude":"26.4718","depth":"5.4","md":"-.-","ml":"2.0","mw":"-.-","location":"ONIKI ADALAR (AKDENIZ)"},{"date":"2020.11.02","time":"13:00:59","latitude":"37.8742","longitude":"26.9547","depth":"7.9","md":"-.-","ml":"1.9","mw":"-.-","location":"KUSADASI KORFEZI (EGE DENIZI)"},{"date":"2020.11.02","time":"12:59:01","latitude":"37.8540","longitude":"26.9118","depth":"4.4","md":"-.-","ml":"1.9","mw":"-.-","location":"KUSADASI KORFEZI (EGE DENIZI)"},{"date":"2020.11.02","time":"12:49:58","latitude":"37.8430","longitude":"26.4800","depth":"5.5","md":"-.-","ml":"2.4","mw":"-.-","location":"SISAM ADASI (EGE DENIZI)"},{"date":"2020.11.02","time":"12:46:21","latitude":"39.2043","longitude":"27.8172","depth":"0.0","md":"-.-","ml":"2.2","mw":"-.-","location":"ALACALAR-KIRKAGAC (MANISA)"},{"date":"2020.11.02","time":"12:39:29","latitude":"37.8450","longitude":"26.9290","depth":"9.3","md":"-.-","ml":"2.4","mw":"-.-","location":"KUSADASI KORFEZI (EGE DENIZI)"},{"date":"2020.11.02","time":"12:36:12","latitude":"37.7880","longitude":"26.9527","depth":"7.4","md":"-.-","ml":"2.0","mw":"-.-","location":"SISAM ADASI (EGE DENIZI)"},{"date":"2020.11.02","time":"12:35:08","latitude":"37.8428","longitude":"26.7815","depth":"5.4","md":"-.-","ml":"2.4","mw":"-.-","location":"EGE DENIZI"},{"date":"2020.11.02","time":"12:33:30","latitude":"37.8822","longitude":"27.1567","depth":"5.4","md":"-.-","ml":"2.1","mw":"-.-","location":"KUSADASI KORFEZI (EGE DENIZI)"},{"date":"2020.11.02","time":"12:28:32","latitude":"37.7928","longitude":"26.9612","depth":"7.3","md":"-.-","ml":"2.4","mw":"-.-","location":"SISAM ADASI (EGE DENIZI)"},{"date":"2020.11.02","time":"12:10:18","latitude":"37.7757","longitude":"27.0568","depth":"2.6","md":"-.-","ml":"1.8","mw":"-.-","location":"KUSADASI KORFEZI (EGE DENIZI)"},{"date":"2020.11.02","time":"12:09:16","latitude":"37.7737","longitude":"27.2338","depth":"5.0","md":"-.-","ml":"2.0","mw":"-.-","location":"KUSADASI KORFEZI (EGE DENIZI)"},{"date":"2020.11.02","time":"12:08:41","latitude":"37.0803","longitude":"37.5657","depth":"8.0","md":"-.-","ml":"1.8","mw":"-.-","location":"BATTAL-SEHITKAMIL (GAZIANTEP)"},{"date":"2020.11.02","time":"11:58:37","latitude":"37.8343","longitude":"26.8640","depth":"5.0","md":"-.-","ml":"2.9","mw":"-.-","location":"SISAM ADASI (EGE DENIZI)"},{"date":"2020.11.02","time":"11:56:41","latitude":"37.7688","longitude":"27.0875","depth":"2.7","md":"-.-","ml":"2.0","mw":"-.-","location":"KUSADASI KORFEZI (EGE DENIZI)"},{"date":"2020.11.02","time":"11:48:48","latitude":"37.9333","longitude":"26.9948","depth":"4.9","md":"-.-","ml":"1.7","mw":"-.-","location":"KUSADASI KORFEZI (EGE DENIZI)"},{"date":"2020.11.02","time":"11:47:08","latitude":"36.2653","longitude":"33.7148","depth":"0.0","md":"-.-","ml":"1.3","mw":"-.-","location":"ISIKLI-SILIFKE (MERSIN)"},{"date":"2020.11.02","time":"11:39:44","latitude":"37.8443","longitude":"26.9445","depth":"3.9","md":"-.-","ml":"2.0","mw":"-.-","location":"KUSADASI KORFEZI (EGE DENIZI)"},{"date":"2020.11.02","time":"11:36:46","latitude":"37.7638","longitude":"27.0935","depth":"3.3","md":"-.-","ml":"2.1","mw":"-.-","location":"KUSADASI KORFEZI (EGE DENIZI)"},{"date":"2020.11.02","time":"11:32:17","latitude":"37.8093","longitude":"26.9653","depth":"6.2","md":"-.-","ml":"2.0","mw":"-.-","location":"KUSADASI KORFEZI (EGE DENIZI)"},{"date":"2020.11.02","time":"11:31:19","latitude":"37.8077","longitude":"26.7517","depth":"2.9","md":"-.-","ml":"2.4","mw":"-.-","location":"EGE DENIZI"},{"date":"2020.11.02","time":"11:21:46","latitude":"37.8275","longitude":"26.8725","depth":"5.0","md":"-.-","ml":"2.2","mw":"-.-","location":"SISAM ADASI (EGE DENIZI)"},{"date":"2020.11.02","time":"11:08:40","latitude":"37.8772","longitude":"27.1273","depth":"9.0","md":"-.-","ml":"1.9","mw":"-.-","location":"KUSADASI KORFEZI (EGE DENIZI)"},{"date":"2020.11.02","time":"11:07:20","latitude":"35.5578","longitude":"29.3800","depth":"26.2","md":"-.-","ml":"1.8","mw":"-.-","location":"AKDENIZ"},{"date":"2020.11.02","time":"11:05:49","latitude":"37.8788","longitude":"26.9953","depth":"3.4","md":"-.-","ml":"1.9","mw":"-.-","location":"KUSADASI KORFEZI (EGE DENIZI)"},{"date":"2020.11.02","time":"11:01:36","latitude":"37.8737","longitude":"26.8528","depth":"5.0","md":"-.-","ml":"2.1","mw":"-.-","location":"KUSADASI KORFEZI (EGE DENIZI)"},{"date":"2020.11.02","time":"10:57:05","latitude":"38.1588","longitude":"27.3280","depth":"4.4","md":"-.-","ml":"3.8","mw":"3.6","location":"KAPLANCIK-TORBALI (IZMIR)"},{"date":"2020.11.02","time":"10:51:11","latitude":"37.9280","longitude":"26.8993","depth":"5.9","md":"-.-","ml":"1.9","mw":"-.-","location":"KUSADASI KORFEZI (EGE DENIZI)"},{"date":"2020.11.02","time":"10:49:04","latitude":"37.8157","longitude":"26.4650","depth":"5.0","md":"-.-","ml":"2.2","mw":"-.-","location":"ONIKI ADALAR (AKDENIZ)"},{"date":"2020.11.02","time":"10:47:45","latitude":"37.8935","longitude":"26.8828","depth":"7.9","md":"-.-","ml":"2.0","mw":"-.-","location":"KUSADASI KORFEZI (EGE DENIZI)"},{"date":"2020.11.02","time":"10:45:37","latitude":"37.8792","longitude":"26.9427","depth":"8.1","md":"-.-","ml":"2.0","mw":"-.-","location":"KUSADASI KORFEZI (EGE DENIZI)"},{"date":"2020.11.02","time":"10:41:51","latitude":"37.8917","longitude":"26.8697","depth":"5.6","md":"-.-","ml":"1.7","mw":"-.-","location":"KUSADASI KORFEZI (EGE DENIZI)"},{"date":"2020.11.02","time":"10:36:55","latitude":"37.9085","longitude":"26.9133","depth":"8.1","md":"-.-","ml":"2.0","mw":"-.-","location":"KUSADASI KORFEZI (EGE DENIZI)"},{"date":"2020.11.02","time":"10:33:43","latitude":"37.9182","longitude":"26.4690","depth":"1.6","md":"-.-","ml":"2.1","mw":"-.-","location":"EGE DENIZI"},{"date":"2020.11.02","time":"10:23:12","latitude":"37.8783","longitude":"26.5062","depth":"13.8","md":"-.-","ml":"2.2","mw":"-.-","location":"EGE DENIZI"},{"date":"2020.11.02","time":"10:15:55","latitude":"37.8983","longitude":"26.4848","depth":"7.4","md":"-.-","ml":"2.3","mw":"-.-","location":"EGE DENIZI"},{"date":"2020.11.02","time":"10:10:35","latitude":"37.7932","longitude":"26.8765","depth":"7.9","md":"-.-","ml":"2.0","mw":"-.-","location":"SISAM ADASI (EGE DENIZI)"},{"date":"2020.11.02","time":"10:09:20","latitude":"38.8967","longitude":"26.0020","depth":"8.2","md":"-.-","ml":"2.8","mw":"-.-","location":"EGE DENIZI"},{"date":"2020.11.02","time":"10:08:34","latitude":"38.8977","longitude":"30.1238","depth":"5.1","md":"-.-","ml":"2.2","mw":"-.-","location":"SELKISARAY-DUMLUPINAR (KUTAHYA)"},{"date":"2020.11.02","time":"10:02:25","latitude":"37.7328","longitude":"27.1210","depth":"3.8","md":"-.-","ml":"2.1","mw":"-.-","location":"KUSADASI KORFEZI (EGE DENIZI)"},{"date":"2020.11.02","time":"09:59:24","latitude":"37.8278","longitude":"26.5607","depth":"8.1","md":"-.-","ml":"2.0","mw":"-.-","location":"SISAM ADASI (EGE DENIZI)"},{"date":"2020.11.02","time":"09:54:59","latitude":"37.9928","longitude":"27.1475","depth":"1.5","md":"-.-","ml":"2.1","mw":"-.-","location":"KUSADASI KORFEZI (EGE DENIZI)"},{"date":"2020.11.02","time":"09:43:09","latitude":"37.7747","longitude":"27.0803","depth":"20.1","md":"-.-","ml":"2.1","mw":"-.-","location":"KUSADASI KORFEZI (EGE DENIZI)"},{"date":"2020.11.02","time":"09:29:11","latitude":"37.8847","longitude":"26.9302","depth":"4.4","md":"-.-","ml":"2.1","mw":"-.-","location":"KUSADASI KORFEZI (EGE DENIZI)"},{"date":"2020.11.02","time":"09:26:45","latitude":"37.9210","longitude":"26.6488","depth":"10.1","md":"-.-","ml":"2.2","mw":"-.-","location":"EGE DENIZI"},{"date":"2020.11.02","time":"09:22:18","latitude":"38.3727","longitude":"27.6502","depth":"7.6","md":"-.-","ml":"3.7","mw":"3.5","location":"OVACIK-KEMALPASA (IZMIR)"},{"date":"2020.11.02","time":"09:12:27","latitude":"37.8258","longitude":"26.7542","depth":"9.8","md":"-.-","ml":"2.1","mw":"-.-","location":"EGE DENIZI"},{"date":"2020.11.02","time":"08:56:37","latitude":"37.9020","longitude":"26.9422","depth":"15.8","md":"-.-","ml":"2.3","mw":"-.-","location":"KUSADASI KORFEZI (EGE DENIZI)"},{"date":"2020.11.02","time":"08:55:24","latitude":"37.7992","longitude":"26.6967","depth":"10.6","md":"-.-","ml":"3.2","mw":"-.-","location":"SISAM ADASI (EGE DENIZI)"},{"date":"2020.11.02","time":"08:45:35","latitude":"37.9345","longitude":"26.7635","depth":"2.8","md":"-.-","ml":"2.0","mw":"-.-","location":"EGE DENIZI"},{"date":"2020.11.02","time":"08:33:58","latitude":"37.9122","longitude":"26.4377","depth":"7.4","md":"-.-","ml":"2.0","mw":"-.-","location":"EGE DENIZI"},{"date":"2020.11.02","time":"08:32:49","latitude":"37.9150","longitude":"26.8187","depth":"8.0","md":"-.-","ml":"2.2","mw":"-.-","location":"EGE DENIZI"},{"date":"2020.11.02","time":"08:31:55","latitude":"37.8907","longitude":"26.8518","depth":"10.9","md":"-.-","ml":"2.2","mw":"-.-","location":"KUSADASI KORFEZI (EGE DENIZI)"},{"date":"2020.11.02","time":"08:26:34","latitude":"37.8227","longitude":"26.9673","depth":"5.0","md":"-.-","ml":"2.1","mw":"-.-","location":"KUSADASI KORFEZI (EGE DENIZI)"},{"date":"2020.11.02","time":"08:24:51","latitude":"37.8460","longitude":"26.8242","depth":"1.1","md":"-.-","ml":"1.9","mw":"-.-","location":"EGE DENIZI"},{"date":"2020.11.02","time":"08:21:59","latitude":"37.8335","longitude":"26.5023","depth":"5.0","md":"-.-","ml":"3.5","mw":"-.-","location":"SISAM ADASI (EGE DENIZI)"},{"date":"2020.11.02","time":"08:16:03","latitude":"37.8760","longitude":"27.1285","depth":"5.4","md":"-.-","ml":"2.5","mw":"-.-","location":"KUSADASI KORFEZI (EGE DENIZI)"},{"date":"2020.11.02","time":"08:12:30","latitude":"37.8803","longitude":"26.6965","depth":"9.5","md":"-.-","ml":"2.7","mw":"-.-","location":"EGE DENIZI"},{"date":"2020.11.02","time":"08:06:30","latitude":"37.8277","longitude":"27.0108","depth":"8.6","md":"-.-","ml":"1.7","mw":"-.-","location":"KUSADASI KORFEZI (EGE DENIZI)"},{"date":"2020.11.02","time":"08:03:01","latitude":"38.2777","longitude":"31.1955","depth":"5.0","md":"-.-","ml":"2.8","mw":"-.-","location":"YALVAC (ISPARTA)"},{"date":"2020.11.02","time":"07:57:39","latitude":"37.9417","longitude":"27.0207","depth":"5.4","md":"-.-","ml":"2.0","mw":"-.-","location":"KUSADASI KORFEZI (EGE DENIZI)"},{"date":"2020.11.02","time":"07:52:44","latitude":"37.8422","longitude":"26.8217","depth":"3.4","md":"-.-","ml":"2.1","mw":"-.-","location":"EGE DENIZI"},{"date":"2020.11.02","time":"07:50:22","latitude":"38.9283","longitude":"27.8992","depth":"5.0","md":"-.-","ml":"1.7","mw":"-.-","location":"HASKOY-AKHISAR (MANISA)"},{"date":"2020.11.02","time":"07:50:13","latitude":"37.8713","longitude":"26.9227","depth":"10.3","md":"-.-","ml":"2.0","mw":"-.-","location":"KUSADASI KORFEZI (EGE DENIZI)"},{"date":"2020.11.02","time":"07:46:39","latitude":"37.7852","longitude":"27.2610","depth":"7.7","md":"-.-","ml":"1.6","mw":"-.-","location":"SOGUCAK-KUSADASI (AYDIN)"},{"date":"2020.11.02","time":"07:42:08","latitude":"37.8240","longitude":"26.7282","depth":"8.3","md":"-.-","ml":"2.2","mw":"-.-","location":"EGE DENIZI"},{"date":"2020.11.02","time":"07:36:57","latitude":"37.8305","longitude":"26.3833","depth":"5.7","md":"-.-","ml":"1.9","mw":"-.-","location":"ONIKI ADALAR (AKDENIZ)"},{"date":"2020.11.02","time":"07:34:04","latitude":"39.0758","longitude":"25.4745","depth":"29.6","md":"-.-","ml":"2.4","mw":"-.-","location":"EGE DENIZI"},{"date":"2020.11.02","time":"07:32:40","latitude":"37.8595","longitude":"26.8858","depth":"10.1","md":"-.-","ml":"2.6","mw":"-.-","location":"KUSADASI KORFEZI (EGE DENIZI)"},{"date":"2020.11.02","time":"07:30:07","latitude":"37.8138","longitude":"26.7210","depth":"8.2","md":"-.-","ml":"3.7","mw":"3.7","location":"SISAM ADASI (EGE DENIZI)"},{"date":"2020.11.02","time":"07:25:26","latitude":"37.8053","longitude":"26.4178","depth":"5.0","md":"-.-","ml":"3.0","mw":"-.-","location":"ONIKI ADALAR (AKDENIZ)"},{"date":"2020.11.02","time":"07:24:39","latitude":"37.8198","longitude":"26.6950","depth":"11.2","md":"-.-","ml":"2.4","mw":"-.-","location":"SISAM ADASI (EGE DENIZI)"},{"date":"2020.11.02","time":"07:20:26","latitude":"37.9598","longitude":"26.5563","depth":"5.0","md":"-.-","ml":"1.9","mw":"-.-","location":"EGE DENIZI"},{"date":"2020.11.02","time":"07:17:29","latitude":"37.8388","longitude":"26.7450","depth":"3.0","md":"-.-","ml":"1.9","mw":"-.-","location":"EGE DENIZI"},{"date":"2020.11.02","time":"07:11:20","latitude":"37.8902","longitude":"27.0372","depth":"5.0","md":"-.-","ml":"2.0","mw":"-.-","location":"KUSADASI KORFEZI (EGE DENIZI)"},{"date":"2020.11.02","time":"07:08:10","latitude":"37.9050","longitude":"26.9562","depth":"10.9","md":"-.-","ml":"2.7","mw":"-.-","location":"KUSADASI KORFEZI (EGE DENIZI)"},{"date":"2020.11.02","time":"07:07:53","latitude":"37.9675","longitude":"27.3517","depth":"4.6","md":"-.-","ml":"2.1","mw":"-.-","location":"SELCUK (IZMIR)"},{"date":"2020.11.02","time":"07:03:23","latitude":"37.8473","longitude":"26.5102","depth":"7.6","md":"-.-","ml":"1.9","mw":"-.-","location":"SISAM ADASI (EGE DENIZI)"},{"date":"2020.11.02","time":"07:00:41","latitude":"37.9953","longitude":"27.0940","depth":"8.1","md":"-.-","ml":"2.2","mw":"-.-","location":"KUSADASI KORFEZI (EGE DENIZI)"},{"date":"2020.11.02","time":"06:59:33","latitude":"37.8912","longitude":"26.9532","depth":"11.8","md":"-.-","ml":"1.6","mw":"-.-","location":"KUSADASI KORFEZI (EGE DENIZI)"},{"date":"2020.11.02","time":"06:54:45","latitude":"37.8662","longitude":"26.6822","depth":"5.3","md":"-.-","ml":"2.1","mw":"-.-","location":"EGE DENIZI"},{"date":"2020.11.02","time":"06:52:27","latitude":"37.7547","longitude":"26.9060","depth":"5.8","md":"-.-","ml":"2.0","mw":"-.-","location":"SISAM ADASI (EGE DENIZI)"},{"date":"2020.11.02","time":"06:48:17","latitude":"37.8857","longitude":"26.9527","depth":"5.3","md":"-.-","ml":"1.9","mw":"-.-","location":"KUSADASI KORFEZI (EGE DENIZI)"},{"date":"2020.11.02","time":"06:45:50","latitude":"37.8642","longitude":"26.9065","depth":"10.7","md":"-.-","ml":"3.2","mw":"3.2","location":"KUSADASI KORFEZI (EGE DENIZI)"},{"date":"2020.11.02","time":"06:44:32","latitude":"37.9318","longitude":"26.5230","depth":"12.6","md":"-.-","ml":"1.7","mw":"-.-","location":"EGE DENIZI"},{"date":"2020.11.02","time":"06:43:54","latitude":"37.8282","longitude":"26.4947","depth":"9.5","md":"-.-","ml":"2.0","mw":"-.-","location":"SISAM ADASI (EGE DENIZI)"},{"date":"2020.11.02","time":"06:41:12","latitude":"37.8637","longitude":"26.8937","depth":"6.1","md":"-.-","ml":"2.0","mw":"-.-","location":"KUSADASI KORFEZI (EGE DENIZI)"},{"date":"2020.11.02","time":"06:39:56","latitude":"37.8140","longitude":"26.7017","depth":"2.5","md":"-.-","ml":"2.0","mw":"-.-","location":"SISAM ADASI (EGE DENIZI)"},{"date":"2020.11.02","time":"06:18:07","latitude":"37.8992","longitude":"26.5023","depth":"3.6","md":"-.-","ml":"2.2","mw":"-.-","location":"EGE DENIZI"},{"date":"2020.11.02","time":"06:17:09","latitude":"37.9057","longitude":"26.5090","depth":"5.0","md":"-.-","ml":"2.3","mw":"-.-","location":"EGE DENIZI"},{"date":"2020.11.02","time":"06:14:08","latitude":"37.7858","longitude":"26.6413","depth":"9.2","md":"-.-","ml":"2.8","mw":"-.-","location":"SISAM ADASI (EGE DENIZI)"},{"date":"2020.11.02","time":"06:09:03","latitude":"37.8762","longitude":"27.1482","depth":"6.6","md":"-.-","ml":"2.3","mw":"-.-","location":"KUSADASI KORFEZI (EGE DENIZI)"},{"date":"2020.11.02","time":"06:03:15","latitude":"37.8912","longitude":"26.9283","depth":"13.0","md":"-.-","ml":"1.6","mw":"-.-","location":"KUSADASI KORFEZI (EGE DENIZI)"},{"date":"2020.11.02","time":"05:54:45","latitude":"37.8357","longitude":"26.7728","depth":"5.8","md":"-.-","ml":"2.7","mw":"-.-","location":"EGE DENIZI"},{"date":"2020.11.02","time":"05:53:14","latitude":"37.8777","longitude":"26.7647","depth":"5.4","md":"-.-","ml":"2.1","mw":"-.-","location":"EGE DENIZI"},{"date":"2020.11.02","time":"05:52:13","latitude":"37.8157","longitude":"26.8583","depth":"3.3","md":"-.-","ml":"2.3","mw":"-.-","location":"SISAM ADASI (EGE DENIZI)"},{"date":"2020.11.02","time":"05:49:29","latitude":"37.7557","longitude":"26.3852","depth":"8.5","md":"-.-","ml":"2.8","mw":"-.-","location":"ONIKI ADALAR (AKDENIZ)"},{"date":"2020.11.02","time":"05:44:16","latitude":"36.8143","longitude":"29.1958","depth":"1.5","md":"-.-","ml":"2.2","mw":"-.-","location":"SOGUTLU-FETHIYE (MUGLA)"},{"date":"2020.11.02","time":"05:40:45","latitude":"37.8465","longitude":"26.4237","depth":"2.5","md":"-.-","ml":"2.4","mw":"-.-","location":"ONIKI ADALAR (AKDENIZ)"},{"date":"2020.11.02","time":"05:35:50","latitude":"37.8265","longitude":"27.1777","depth":"5.9","md":"-.-","ml":"2.0","mw":"-.-","location":"KUSADASI KORFEZI (EGE DENIZI)"},{"date":"2020.11.02","time":"05:29:23","latitude":"37.9113","longitude":"26.4803","depth":"6.6","md":"-.-","ml":"1.8","mw":"-.-","location":"EGE DENIZI"},{"date":"2020.11.02","time":"05:21:40","latitude":"37.8055","longitude":"26.7047","depth":"5.0","md":"-.-","ml":"1.4","mw":"-.-","location":"SISAM ADASI (EGE DENIZI)"},{"date":"2020.11.02","time":"05:20:03","latitude":"37.8675","longitude":"26.8838","depth":"5.8","md":"-.-","ml":"1.7","mw":"-.-","location":"KUSADASI KORFEZI (EGE DENIZI)"},{"date":"2020.11.02","time":"05:13:41","latitude":"37.8693","longitude":"27.0108","depth":"8.0","md":"-.-","ml":"1.9","mw":"-.-","location":"KUSADASI KORFEZI (EGE DENIZI)"},{"date":"2020.11.02","time":"04:57:52","latitude":"37.8752","longitude":"26.8500","depth":"5.2","md":"-.-","ml":"1.8","mw":"-.-","location":"KUSADASI KORFEZI (EGE DENIZI)"},{"date":"2020.11.02","time":"04:51:14","latitude":"37.8890","longitude":"27.0592","depth":"7.8","md":"-.-","ml":"1.8","mw":"-.-","location":"KUSADASI KORFEZI (EGE DENIZI)"},{"date":"2020.11.02","time":"04:47:54","latitude":"38.4780","longitude":"39.2555","depth":"3.7","md":"-.-","ml":"2.2","mw":"-.-","location":"ALINCIK-SIVRICE (ELAZIG)"},{"date":"2020.11.02","time":"04:46:32","latitude":"38.0262","longitude":"27.0902","depth":"7.6","md":"-.-","ml":"1.8","mw":"-.-","location":"KUSADASI KORFEZI (EGE DENIZI)"},{"date":"2020.11.02","time":"04:45:13","latitude":"38.0217","longitude":"27.0840","depth":"5.3","md":"-.-","ml":"1.8","mw":"-.-","location":"KUSADASI KORFEZI (EGE DENIZI)"},{"date":"2020.11.02","time":"04:42:59","latitude":"37.8657","longitude":"26.9227","depth":"5.0","md":"-.-","ml":"2.1","mw":"-.-","location":"KUSADASI KORFEZI (EGE DENIZI)"},{"date":"2020.11.02","time":"04:35:38","latitude":"37.8898","longitude":"26.6907","depth":"4.2","md":"-.-","ml":"1.8","mw":"-.-","location":"EGE DENIZI"},{"date":"2020.11.02","time":"04:31:38","latitude":"37.8875","longitude":"26.6130","depth":"7.1","md":"-.-","ml":"2.7","mw":"-.-","location":"EGE DENIZI"},{"date":"2020.11.02","time":"04:29:10","latitude":"37.9352","longitude":"26.4127","depth":"6.9","md":"-.-","ml":"2.8","mw":"-.-","location":"EGE DENIZI"},{"date":"2020.11.02","time":"04:23:51","latitude":"37.9223","longitude":"27.0865","depth":"5.4","md":"-.-","ml":"1.6","mw":"-.-","location":"KUSADASI KORFEZI (EGE DENIZI)"},{"date":"2020.11.02","time":"04:20:36","latitude":"37.8343","longitude":"26.7460","depth":"10.0","md":"-.-","ml":"3.5","mw":"3.4","location":"EGE DENIZI"},{"date":"2020.11.02","time":"04:12:03","latitude":"37.8735","longitude":"26.7075","depth":"5.5","md":"-.-","ml":"1.4","mw":"-.-","location":"EGE DENIZI"},{"date":"2020.11.02","time":"04:05:41","latitude":"37.8838","longitude":"26.8287","depth":"14.8","md":"-.-","ml":"1.5","mw":"-.-","location":"EGE DENIZI"},{"date":"2020.11.02","time":"04:04:37","latitude":"37.8815","longitude":"26.6710","depth":"9.8","md":"-.-","ml":"1.6","mw":"-.-","location":"EGE DENIZI"},{"date":"2020.11.02","time":"03:57:08","latitude":"37.8740","longitude":"26.9057","depth":"5.7","md":"-.-","ml":"1.9","mw":"-.-","location":"KUSADASI KORFEZI (EGE DENIZI)"},{"date":"2020.11.02","time":"03:54:23","latitude":"37.8860","longitude":"26.8392","depth":"12.9","md":"-.-","ml":"2.0","mw":"-.-","location":"EGE DENIZI"},{"date":"2020.11.02","time":"03:53:30","latitude":"37.8378","longitude":"26.5983","depth":"9.5","md":"-.-","ml":"2.6","mw":"-.-","location":"SISAM ADASI (EGE DENIZI)"},{"date":"2020.11.02","time":"03:50:57","latitude":"37.8113","longitude":"26.7115","depth":"8.3","md":"-.-","ml":"3.0","mw":"-.-","location":"SISAM ADASI (EGE DENIZI)"},{"date":"2020.11.02","time":"03:47:52","latitude":"37.8187","longitude":"26.4222","depth":"8.4","md":"-.-","ml":"2.2","mw":"-.-","location":"ONIKI ADALAR (AKDENIZ)"},{"date":"2020.11.02","time":"03:42:19","latitude":"37.8958","longitude":"26.9535","depth":"5.4","md":"-.-","ml":"1.9","mw":"-.-","location":"KUSADASI KORFEZI (EGE DENIZI)"},{"date":"2020.11.02","time":"03:40:10","latitude":"37.7985","longitude":"26.4775","depth":"5.0","md":"-.-","ml":"2.5","mw":"-.-","location":"ONIKI ADALAR (AKDENIZ)"},{"date":"2020.11.02","time":"03:32:55","latitude":"37.8313","longitude":"26.7105","depth":"5.0","md":"-.-","ml":"2.0","mw":"-.-","location":"EGE DENIZI"},{"date":"2020.11.02","time":"03:22:40","latitude":"37.8785","longitude":"27.1340","depth":"5.8","md":"-.-","ml":"3.0","mw":"3.0","location":"KUSADASI KORFEZI (EGE DENIZI)"},{"date":"2020.11.02","time":"03:21:33","latitude":"37.8053","longitude":"26.4128","depth":"5.0","md":"-.-","ml":"2.5","mw":"-.-","location":"ONIKI ADALAR (AKDENIZ)"},{"date":"2020.11.02","time":"03:19:21","latitude":"37.8360","longitude":"26.9388","depth":"5.0","md":"-.-","ml":"1.9","mw":"-.-","location":"KUSADASI KORFEZI (EGE DENIZI)"},{"date":"2020.11.02","time":"03:17:35","latitude":"37.8907","longitude":"26.6993","depth":"17.2","md":"-.-","ml":"1.8","mw":"-.-","location":"EGE DENIZI"},{"date":"2020.11.02","time":"03:14:41","latitude":"37.8172","longitude":"26.9120","depth":"7.7","md":"-.-","ml":"2.6","mw":"-.-","location":"SISAM ADASI (EGE DENIZI)"},{"date":"2020.11.02","time":"03:06:09","latitude":"37.8552","longitude":"26.9133","depth":"2.7","md":"-.-","ml":"2.2","mw":"-.-","location":"KUSADASI KORFEZI (EGE DENIZI)"},{"date":"2020.11.02","time":"03:05:37","latitude":"36.6673","longitude":"28.1930","depth":"60.3","md":"-.-","ml":"2.0","mw":"-.-","location":"BOZBURUN ACIKLARI-MUGLA (AKDENIZ)"},{"date":"2020.11.02","time":"03:04:30","latitude":"37.8865","longitude":"26.9647","depth":"8.3","md":"-.-","ml":"2.1","mw":"-.-","location":"KUSADASI KORFEZI (EGE DENIZI)"},{"date":"2020.11.02","time":"03:01:00","latitude":"37.8445","longitude":"27.0248","depth":"10.9","md":"-.-","ml":"2.0","mw":"-.-","location":"KUSADASI KORFEZI (EGE DENIZI)"},{"date":"2020.11.02","time":"02:56:37","latitude":"38.0040","longitude":"26.5452","depth":"5.1","md":"-.-","ml":"1.9","mw":"-.-","location":"EGE DENIZI"},{"date":"2020.11.02","time":"02:56:15","latitude":"38.9270","longitude":"43.5613","depth":"2.2","md":"-.-","ml":"1.2","mw":"-.-","location":"COLPAN-(VAN)"},{"date":"2020.11.02","time":"02:55:01","latitude":"37.8765","longitude":"26.8785","depth":"3.1","md":"-.-","ml":"1.9","mw":"-.-","location":"KUSADASI KORFEZI (EGE DENIZI)"},{"date":"2020.11.02","time":"02:52:22","latitude":"37.8483","longitude":"26.9120","depth":"5.2","md":"-.-","ml":"1.8","mw":"-.-","location":"KUSADASI KORFEZI (EGE DENIZI)"},{"date":"2020.11.02","time":"02:50:10","latitude":"37.8995","longitude":"27.2498","depth":"8.6","md":"-.-","ml":"2.3","mw":"-.-","location":"KUSADASI KORFEZI (EGE DENIZI)"},{"date":"2020.11.02","time":"02:49:28","latitude":"37.8663","longitude":"26.8432","depth":"8.0","md":"-.-","ml":"2.6","mw":"-.-","location":"KUSADASI KORFEZI (EGE DENIZI)"},{"date":"2020.11.02","time":"02:44:06","latitude":"37.8638","longitude":"26.8357","depth":"7.5","md":"-.-","ml":"1.9","mw":"-.-","location":"EGE DENIZI"},{"date":"2020.11.02","time":"02:36:51","latitude":"38.0182","longitude":"26.6537","depth":"5.0","md":"-.-","ml":"2.1","mw":"-.-","location":"EGE DENIZI"},{"date":"2020.11.02","time":"02:35:23","latitude":"37.9023","longitude":"26.6928","depth":"7.8","md":"-.-","ml":"1.8","mw":"-.-","location":"EGE DENIZI"},{"date":"2020.11.02","time":"02:26:34","latitude":"38.0440","longitude":"26.1652","depth":"8.3","md":"-.-","ml":"2.9","mw":"-.-","location":"EGE DENIZI"},{"date":"2020.11.02","time":"02:15:48","latitude":"37.8383","longitude":"27.0022","depth":"8.3","md":"-.-","ml":"1.8","mw":"-.-","location":"KUSADASI KORFEZI (EGE DENIZI)"},{"date":"2020.11.02","time":"02:12:17","latitude":"37.8615","longitude":"26.9138","depth":"13.9","md":"-.-","ml":"2.5","mw":"-.-","location":"KUSADASI KORFEZI (EGE DENIZI)"},{"date":"2020.11.02","time":"02:03:40","latitude":"37.8872","longitude":"26.9330","depth":"6.6","md":"-.-","ml":"1.8","mw":"-.-","location":"KUSADASI KORFEZI (EGE DENIZI)"},{"date":"2020.11.02","time":"01:59:33","latitude":"37.8432","longitude":"26.8860","depth":"5.4","md":"-.-","ml":"2.1","mw":"-.-","location":"KUSADASI KORFEZI (EGE DENIZI)"},{"date":"2020.11.02","time":"01:56:54","latitude":"37.8193","longitude":"26.4700","depth":"5.0","md":"-.-","ml":"1.8","mw":"-.-","location":"ONIKI ADALAR (AKDENIZ)"},{"date":"2020.11.02","time":"01:45:09","latitude":"37.8943","longitude":"26.8682","depth":"5.0","md":"-.-","ml":"1.7","mw":"-.-","location":"KUSADASI KORFEZI (EGE DENIZI)"},{"date":"2020.11.02","time":"01:44:23","latitude":"37.7018","longitude":"26.9752","depth":"11.0","md":"-.-","ml":"1.8","mw":"-.-","location":"SISAM ADASI (EGE DENIZI)"},{"date":"2020.11.02","time":"01:42:31","latitude":"37.9452","longitude":"26.6730","depth":"8.0","md":"-.-","ml":"2.1","mw":"-.-","location":"EGE DENIZI"},{"date":"2020.11.02","time":"01:37:37","latitude":"37.7562","longitude":"26.4172","depth":"6.4","md":"-.-","ml":"1.8","mw":"-.-","location":"ONIKI ADALAR (AKDENIZ)"},{"date":"2020.11.02","time":"01:35:20","latitude":"37.8910","longitude":"26.4813","depth":"29.6","md":"-.-","ml":"1.9","mw":"-.-","location":"EGE DENIZI"},{"date":"2020.11.02","time":"01:33:42","latitude":"37.8485","longitude":"26.6245","depth":"9.6","md":"-.-","ml":"3.1","mw":"3.2","location":"SISAM ADASI (EGE DENIZI)"},{"date":"2020.11.02","time":"01:31:45","latitude":"37.8890","longitude":"26.6687","depth":"7.2","md":"-.-","ml":"1.6","mw":"-.-","location":"EGE DENIZI"},{"date":"2020.11.02","time":"01:28:14","latitude":"37.8635","longitude":"26.6375","depth":"5.1","md":"-.-","ml":"2.3","mw":"-.-","location":"EGE DENIZI"},{"date":"2020.11.02","time":"01:24:11","latitude":"37.8683","longitude":"26.9780","depth":"5.5","md":"-.-","ml":"2.3","mw":"-.-","location":"KUSADASI KORFEZI (EGE DENIZI)"},{"date":"2020.11.02","time":"01:14:36","latitude":"37.8942","longitude":"26.9347","depth":"19.8","md":"-.-","ml":"1.7","mw":"-.-","location":"KUSADASI KORFEZI (EGE DENIZI)"},{"date":"2020.11.02","time":"01:11:02","latitude":"37.9528","longitude":"26.6055","depth":"6.5","md":"-.-","ml":"2.4","mw":"-.-","location":"EGE DENIZI"},{"date":"2020.11.02","time":"01:10:01","latitude":"37.8423","longitude":"26.9947","depth":"12.7","md":"-.-","ml":"2.2","mw":"-.-","location":"KUSADASI KORFEZI (EGE DENIZI)"},{"date":"2020.11.02","time":"01:08:58","latitude":"37.7118","longitude":"27.1732","depth":"15.8","md":"-.-","ml":"2.1","mw":"-.-","location":"GUZELCAMLI-KUSADASI (AYDIN)"},{"date":"2020.11.02","time":"01:03:10","latitude":"37.8332","longitude":"26.9392","depth":"5.0","md":"-.-","ml":"2.1","mw":"-.-","location":"KUSADASI KORFEZI (EGE DENIZI)"},{"date":"2020.11.02","time":"01:01:02","latitude":"37.8213","longitude":"26.4522","depth":"8.1","md":"-.-","ml":"2.9","mw":"2.9","location":"ONIKI ADALAR (AKDENIZ)"},{"date":"2020.11.02","time":"00:55:24","latitude":"37.7925","longitude":"26.9238","depth":"9.1","md":"-.-","ml":"2.7","mw":"-.-","location":"SISAM ADASI (EGE DENIZI)"},{"date":"2020.11.02","time":"00:46:05","latitude":"37.8867","longitude":"26.9573","depth":"8.1","md":"-.-","ml":"2.4","mw":"-.-","location":"KUSADASI KORFEZI (EGE DENIZI)"},{"date":"2020.11.02","time":"00:29:18","latitude":"37.9585","longitude":"26.7382","depth":"15.6","md":"-.-","ml":"2.2","mw":"-.-","location":"EGE DENIZI"},{"date":"2020.11.02","time":"00:24:28","latitude":"37.8557","longitude":"26.8998","depth":"19.6","md":"-.-","ml":"2.0","mw":"-.-","location":"KUSADASI KORFEZI (EGE DENIZI)"},{"date":"2020.11.02","time":"00:23:55","latitude":"37.9155","longitude":"26.9572","depth":"13.4","md":"-.-","ml":"1.6","mw":"-.-","location":"KUSADASI KORFEZI (EGE DENIZI)"},{"date":"2020.11.02","time":"00:19:51","latitude":"37.8002","longitude":"26.7060","depth":"17.1","md":"-.-","ml":"2.2","mw":"-.-","location":"SISAM ADASI (EGE DENIZI)"},{"date":"2020.11.02","time":"00:18:07","latitude":"37.9018","longitude":"27.1160","depth":"4.3","md":"-.-","ml":"2.0","mw":"-.-","location":"KUSADASI KORFEZI (EGE DENIZI)"},{"date":"2020.11.02","time":"00:14:47","latitude":"37.8410","longitude":"27.2205","depth":"5.0","md":"-.-","ml":"1.8","mw":"-.-","location":"KUSADASI (AYDIN)"},{"date":"2020.11.02","time":"00:13:42","latitude":"37.7998","longitude":"26.9522","depth":"5.4","md":"-.-","ml":"2.0","mw":"-.-","location":"SISAM ADASI (EGE DENIZI)"},{"date":"2020.11.01","time":"23:58:48","latitude":"40.7570","longitude":"29.2793","depth":"4.1","md":"-.-","ml":"0.8","mw":"-.-","location":"YALOVA ACIKLARI (MARMARA DENIZI)"},{"date":"2020.11.01","time":"23:56:23","latitude":"38.7927","longitude":"26.9743","depth":"22.9","md":"-.-","ml":"2.1","mw":"-.-","location":"ALIAGA (IZMIR)"},{"date":"2020.11.01","time":"23:53:41","latitude":"37.9837","longitude":"27.1222","depth":"7.8","md":"-.-","ml":"3.1","mw":"-.-","location":"KUSADASI KORFEZI (EGE DENIZI)"},{"date":"2020.11.01","time":"23:48:30","latitude":"37.9337","longitude":"26.9945","depth":"5.0","md":"-.-","ml":"2.4","mw":"-.-","location":"KUSADASI KORFEZI (EGE DENIZI)"},{"date":"2020.11.01","time":"23:45:30","latitude":"37.7997","longitude":"26.6693","depth":"15.3","md":"-.-","ml":"1.9","mw":"-.-","location":"SISAM ADASI (EGE DENIZI)"},{"date":"2020.11.01","time":"23:41:30","latitude":"37.8402","longitude":"26.9777","depth":"7.1","md":"-.-","ml":"1.9","mw":"-.-","location":"KUSADASI KORFEZI (EGE DENIZI)"},{"date":"2020.11.01","time":"23:38:27","latitude":"37.8957","longitude":"26.9437","depth":"9.8","md":"-.-","ml":"1.8","mw":"-.-","location":"KUSADASI KORFEZI (EGE DENIZI)"},{"date":"2020.11.01","time":"23:36:51","latitude":"37.9478","longitude":"26.9688","depth":"11.3","md":"-.-","ml":"2.0","mw":"-.-","location":"KUSADASI KORFEZI (EGE DENIZI)"},{"date":"2020.11.01","time":"23:33:56","latitude":"37.8967","longitude":"26.8998","depth":"16.5","md":"-.-","ml":"2.1","mw":"-.-","location":"KUSADASI KORFEZI (EGE DENIZI)"},{"date":"2020.11.01","time":"23:26:17","latitude":"37.8195","longitude":"26.5702","depth":"5.9","md":"-.-","ml":"2.3","mw":"-.-","location":"SISAM ADASI (EGE DENIZI)"},{"date":"2020.11.01","time":"23:25:17","latitude":"37.9317","longitude":"26.5763","depth":"12.5","md":"-.-","ml":"1.6","mw":"-.-","location":"EGE DENIZI"},{"date":"2020.11.01","time":"23:21:41","latitude":"37.7808","longitude":"26.9588","depth":"5.0","md":"-.-","ml":"2.1","mw":"-.-","location":"SISAM ADASI (EGE DENIZI)"}]
